Workbook

Sheet RAT
B1: RAT - RELATÓRIO DE ATENDIMENTO
B2: EXECUÇÃO DOS SERVIÇOS
B3: Número da solicitação | D3: Data/hora Abertura | G3: Contrato de Manutenção | J3: Contratada
B4: 250195016 | D4: 46361 | G4: 2025.7421.0908 | J4: MAFFENG ENGENHARIA E MANUTENÇÃO
B5: Sinistro | D5: Prazo de atendimento | G5: Tipo de Manutenção | J5: Nível de Ocorrência
B6: (Sim/Não) | G6: (Preventiva/Corretiva) | J6: (Emergencial/Urgente/Normal)
B7: Não | D7: 46080 | G7: Preventiva | J7: Normal
B8: Prefixo / SB - Dependência Beneficiada | G8: Endereço
B9: 7027 | C9: =VLOOKUP(B9,Prefixos!A4:E112,3,0) -> VILA TATETUBA | G9: =VLOOKUP(B9,Prefixos!A4:E112,4,0) -> AV.PRES.JUSCELINO KUBITSCHEK 8260
B10: Informações de Contato | G10: Matrícula / Nome - Funcionário Solicitante
B11: Responsável | G11: F6798701 - SISTEMA
B12: SERVIÇOS SOLICITADOS - Portal de Manutenção
B13: Descrição do serviço, Tipo, Quantidade, Local de Atendimento e Prioridade* | K13: Situação (Código**)
B14: Levantamento Preventivo | K14: 4
B15: * Preencher com as informações do Portal de Manutenção da DISEC. ** Preencher o campo situação com os códigos a seguir: 1. Serviço concluído sem pendências; 2. Serviço cancelado pelo demandante; 3. Atendimento Parcial; 4. Confecção de orçamento, para execução do serviço demanda autorização por parte do CESUP Suprimentos; 5. Não Atendido. 6. Mitigação de Riscos ou primeiro atendimento
B16: ORÇAMENTO DOS SERVIÇOS REALIZADOS
B17: ITEM | C17: DESCRIÇÃO | I17: QTD. | J17: UND. | K17: VALOR UNITÁRIO | M17: MAT UNIT | N17: MAO. UNIT | O17: MAT TOTAL | P17: MAO TOTAL | Q17: VALOR TOTAL
B18: 1.2 | C18: =UPPER(VLOOKUP(B18,Valores!$A$7:$J$537,2,0)) -> DESLOCAMENTO | I18: 15 | J18: =UPPER(VLOOKUP(B18,Valores!$A$7:$J$537,4,0)) -> KM | K18: =UPPER(VLOOKUP(B18,Valores!$A$7:$J$537,7,0)) -> 2,15 | M18: =UPPER(VLOOKUP(B18,Valores!$A$7:$J$537,5,0)) -> 1,51 | N18: =UPPER(VLOOKUP(B18,Valores!$A$7:$J$537,6,0)) -> 0,64 | O18: =M18*I18 -> 22.65 | P18: =N18*I18 -> 9.6 | Q18: =K18*I18 -> 32.25
B19: 1.1 | C19: =UPPER(VLOOKUP(B19,Valores!$A$7:$J$537,2,0)) -> CHAMADO | I19: 1 | J19: =UPPER(VLOOKUP(B19,Valores!$A$7:$J$537,4,0)) -> UN | K19: =UPPER(VLOOKUP(B19,Valores!$A$7:$J$537,7,0)) -> 76,34 | M19: =UPPER(VLOOKUP(B19,Valores!$A$7:$J$537,5,0)) -> 0 | N19: =UPPER(VLOOKUP(B19,Valores!$A$7:$J$537,6,0)) -> 76,34 | O19: =M19*I19 -> 0 | P19: =N19*I19 -> 76.34 | Q19: =K19*I19 -> 76.34
C20: =UPPER(VLOOKUP(B20,Valores!$A$7:$J$537,2,0)) -> #N/A | J20: =UPPER(VLOOKUP(B20,Valores!$A$7:$J$537,4,0)) -> #N/A | K20: =UPPER(VLOOKUP(B20,Valores!$A$7:$J$537,7,0)) -> #N/A | M20: =UPPER(VLOOKUP(B20,Valores!$A$7:$J$537,5,0)) -> #N/A | N20: =UPPER(VLOOKUP(B20,Valores!$A$7:$J$537,6,0)) -> #N/A | O20: =M20*I20 -> #N/A | P20: =N20*I20 -> #N/A | Q20: =K20*I20 -> #N/A
C21: =UPPER(VLOOKUP(B21,Valores!$A$7:$J$537,2,0)) -> #N/A | J21: =UPPER(VLOOKUP(B21,Valores!$A$7:$J$537,4,0)) -> #N/A | K21: =UPPER(VLOOKUP(B21,Valores!$A$7:$J$537,7,0)) -> #N/A | M21: =UPPER(VLOOKUP(B21,Valores!$A$7:$J$537,5,0)) -> #N/A | N21: =UPPER(VLOOKUP(B21,Valores!$A$7:$J$537,6,0)) -> #N/A | O21: =M21*I21 -> #N/A | P21: =N21*I21 -> #N/A | Q21: =K21*I21 -> #N/A
C22: =UPPER(VLOOKUP(B22,Valores!$A$7:$J$537,2,0)) -> #N/A | J22: =UPPER(VLOOKUP(B22,Valores!$A$7:$J$537,4,0)) -> #N/A | K22: =UPPER(VLOOKUP(B22,Valores!$A$7:$J$537,7,0)) -> #N/A | M22: =UPPER(VLOOKUP(B22,Valores!$A$7:$J$537,5,0)) -> #N/A | N22: =UPPER(VLOOKUP(B22,Valores!$A$7:$J$537,6,0)) -> #N/A | O22: =M22*I22 -> #N/A | P22: =N22*I22 -> #N/A | Q22: =K22*I22 -> #N/A
C23: =UPPER(VLOOKUP(B23,Valores!$A$7:$J$537,2,0)) -> #N/A | J23: =UPPER(VLOOKUP(B23,Valores!$A$7:$J$537,4,0)) -> #N/A | K23: =UPPER(VLOOKUP(B23,Valores!$A$7:$J$537,7,0)) -> #N/A | M23: =UPPER(VLOOKUP(B23,Valores!$A$7:$J$537,5,0)) -> #N/A | N23: =UPPER(VLOOKUP(B23,Valores!$A$7:$J$537,6,0)) -> #N/A | O23: =M23*I23 -> #N/A | P23: =N23*I23 -> #N/A | Q23: =K23*I23 -> #N/A
C24: =UPPER(VLOOKUP(B24,Valores!$A$7:$J$537,2,0)) -> #N/A | J24: =UPPER(VLOOKUP(B24,Valores!$A$7:$J$537,4,0)) -> #N/A | K24: =UPPER(VLOOKUP(B24,Valores!$A$7:$J$537,7,0)) -> #N/A | M24: =UPPER(VLOOKUP(B24,Valores!$A$7:$J$537,5,0)) -> #N/A | N24: =UPPER(VLOOKUP(B24,Valores!$A$7:$J$537,6,0)) -> #N/A | O24: =M24*I24 -> #N/A | P24: =N24*I24 -> #N/A | Q24: =K24*I24 -> #N/A
C25: =UPPER(VLOOKUP(B25,Valores!$A$7:$J$537,2,0)) -> #N/A | J25: =UPPER(VLOOKUP(B25,Valores!$A$7:$J$537,4,0)) -> #N/A | K25: =UPPER(VLOOKUP(B25,Valores!$A$7:$J$537,7,0)) -> #N/A | M25: =UPPER(VLOOKUP(B25,Valores!$A$7:$J$537,5,0)) -> #N/A | N25: =UPPER(VLOOKUP(B25,Valores!$A$7:$J$537,6,0)) -> #N/A | O25: =M25*I25 -> #N/A | P25: =N25*I25 -> #N/A | Q25: =K25*I25 -> #N/A
C26: =UPPER(VLOOKUP(B26,Valores!$A$7:$J$537,2,0)) -> #N/A | J26: =UPPER(VLOOKUP(B26,Valores!$A$7:$J$537,4,0)) -> #N/A | K26: =UPPER(VLOOKUP(B26,Valores!$A$7:$J$537,7,0)) -> #N/A | M26: =UPPER(VLOOKUP(B26,Valores!$A$7:$J$537,5,0)) -> #N/A | N26: =UPPER(VLOOKUP(B26,Valores!$A$7:$J$537,6,0)) -> #N/A | O26: =M26*I26 -> #N/A | P26: =N26*I26 -> #N/A | Q26: =K26*I26 -> #N/A
C27: =UPPER(VLOOKUP(B27,Valores!$A$7:$J$537,2,0)) -> #N/A | J27: =UPPER(VLOOKUP(B27,Valores!$A$7:$J$537,4,0)) -> #N/A | K27: =UPPER(VLOOKUP(B27,Valores!$A$7:$J$537,7,0)) -> #N/A | M27: =UPPER(VLOOKUP(B27,Valores!$A$7:$J$537,5,0)) -> #N/A | N27: =UPPER(VLOOKUP(B27,Valores!$A$7:$J$537,6,0)) -> #N/A | O27: =M27*I27 -> #N/A | P27: =N27*I27 -> #N/A | Q27: =K27*I27 -> #N/A
C28: =UPPER(VLOOKUP(B28,Valores!$A$7:$J$537,2,0)) -> #N/A | J28: =UPPER(VLOOKUP(B28,Valores!$A$7:$J$537,4,0)) -> #N/A | K28: =UPPER(VLOOKUP(B28,Valores!$A$7:$J$537,7,0)) -> #N/A | M28: =UPPER(VLOOKUP(B28,Valores!$A$7:$J$537,5,0)) -> #N/A | N28: =UPPER(VLOOKUP(B28,Valores!$A$7:$J$537,6,0)) -> #N/A | O28: =M28*I28 -> #N/A | P28: =N28*I28 -> #N/A | Q28: =K28*I28 -> #N/A
C29: =UPPER(VLOOKUP(B29,Valores!$A$7:$J$537,2,0)) -> #N/A | J29: =UPPER(VLOOKUP(B29,Valores!$A$7:$J$537,4,0)) -> #N/A | K29: =UPPER(VLOOKUP(B29,Valores!$A$7:$J$537,7,0)) -> #N/A | M29: =UPPER(VLOOKUP(B29,Valores!$A$7:$J$537,5,0)) -> #N/A | N29: =UPPER(VLOOKUP(B29,Valores!$A$7:$J$537,6,0)) -> #N/A | O29: =M29*I29 -> #N/A | P29: =N29*I29 -> #N/A | Q29: =K29*I29 -> #N/A
C30: =UPPER(VLOOKUP(B30,Valores!$A$7:$J$537,2,0)) -> #N/A | J30: =UPPER(VLOOKUP(B30,Valores!$A$7:$J$537,4,0)) -> #N/A | K30: =UPPER(VLOOKUP(B30,Valores!$A$7:$J$537,7,0)) -> #N/A | M30: =UPPER(VLOOKUP(B30,Valores!$A$7:$J$537,5,0)) -> #N/A | N30: =UPPER(VLOOKUP(B30,Valores!$A$7:$J$537,6,0)) -> #N/A | O30: =M30*I30 -> #N/A | P30: =N30*I30 -> #N/A | Q30: =K30*I30 -> #N/A
C31: =UPPER(VLOOKUP(B31,Valores!$A$7:$J$537,2,0)) -> #N/A | J31: =UPPER(VLOOKUP(B31,Valores!$A$7:$J$537,4,0)) -> #N/A | K31: =UPPER(VLOOKUP(B31,Valores!$A$7:$J$537,7,0)) -> #N/A | M31: =UPPER(VLOOKUP(B31,Valores!$A$7:$J$537,5,0)) -> #N/A | N31: =UPPER(VLOOKUP(B31,Valores!$A$7:$J$537,6,0)) -> #N/A | O31: =M31*I31 -> #N/A | P31: =N31*I31 -> #N/A | Q31: =K31*I31 -> #N/A
... C50: =UPPER(VLOOKUP(B50,Valores!$A$7:$J$537,2,0)) -> #N/A | J50: =UPPER(VLOOKUP(B50,Valores!$A$7:$J$537,4,0)) -> #N/A | K50: =UPPER(VLOOKUP(B50,Valores!$A$7:$J$537,7,0)) -> #N/A | M50: =UPPER(VLOOKUP(B50,Valores!$A$7:$J$537,5,0)) -> #N/A | N50: =UPPER(VLOOKUP(B50,Valores!$A$7:$J$537,6,0)) -> #N/A | O50: =M50*I50 -> #N/A | P50: =N50*I50 -> #N/A | Q50: =K50*I50 -> #N/A
B51: RESUMO DO ORÇAMENTO DOS SERVIÇOS SOLICITADOS
B52: Data / Hora Conclusão | G52: Valor de Materiais + Mão de Obra | J52: Valor Total
B53: =F68 -> 46078 | G53: =SUM(O18:O50) -> #N/A | H53: + | I53: =SUM(P18:P50) -> #N/A | J53: =I53+G53 -> #N/A
B54: Observações
C58: ________________________________________________ | I58: ___________________________________________________________________________________
C62: VISTO REPRESENTANTE DA EMPRESA CONTRATADA | I62: CARIMBO E VISTO DA DEPENDÊNCIA
B64: TÉCNICO | J64: ENGENHEIRO
J65: ______________________________________
B66: AUXILIAR
B68: Data e hora | C68: 46078 | E68: Data e hora | F68: 46078 | J68: RESPONSÁVEL TÉCNICO
B69: CHEGADA | E69: SAÍDA | J69: CARIMBO - NÚMERO / VISTO DO CREA
B71: O RAT deverá ser emitido em 3 vias sendo, a 1º para a dependência beneficiada, a 2º para a empresa contratada e a 3º CESUP Suprimentos

Sheet Conformidade
A1: RAT - RELATÓRIO DE ATENDIMENTO
A2: Conformidade do atendimento no local dos serviços
A3: Número da solicitação | C3: Data/hora Abertura | F3: Contrato de Manutenção | I3: Contratada
A4: =RAT!B4 -> 250195016 | C4: =RAT!D4 -> 46361 | F4: 2025.7421.0908 | I4: MAFFENG ENGENHARIA E MANUTENÇÃO
A5: Sinistro | C5: Prazo de atendimento | F5: Tipo de Manutenção | I5: Nível de Ocorrência
A6: (Sim/Não) | F6: (Preventiva/Corretiva) | I6: (Emergencial/Urgente/Normal)
A7: =RAT!B7 -> Não | C7: =RAT!D7 -> 46080 | F7: =RAT!G7 -> Preventiva | I7: =RAT!J7 -> Normal
A8: Prefixo / SB - Dependência Beneficiada | F8: Endereço
A9: =RAT!B9 -> 7027 | B9: =RAT!C9 -> VILA TATETUBA | F9: =RAT!G9 -> AV.PRES.JUSCELINO KUBITSCHEK 8260
A10: Informações de Contato | F10: Matrícula / Nome - Funcionário Solicitante
A11: =RAT!B11 -> Responsável | F11: =RAT!G11 -> F6798701 - SISTEMA
A12: MÓDULO DEMANDANTE / BENEFICIÁRIO / CONTRATANTE PREENCHIMENTO PELO PREPOSTO DO BANCO DO BRASIL
A13: Matrícula | C13: Nome Funcionário Preposto
A15: Questionário | I15: Atendeu | K15: Não Atendeu
A16: Prazo de Atendimento
A17: Qualidade dos serviços executados
A18: Discrição e Presteza dos funcionários
A19: RESUMO DO ORÇAMENTO DOS SERVIÇOS EXECUTADOS
A20: Data / Hora Conclusão | F20: Valor de Materiais + Mão de Obra | I20: Valor Total
A21: =RAT!B53 -> 46078 | F21: =RAT!G53 -> #N/A | G21: + | H21: =RAT!I53 -> #N/A | I21: =RAT!J53 -> #N/A
A22: Observações
A24: Sr. ADMINISTRADOR PREDIAL, antes de assinar o RAT (Relatório de Atendimento), deve-se observar que:
A25: 1. A Situação (código, em "Serviços Solicitados") foi preenchida adequadamente para cada serviço solicitado e que os serviços
A26: registrados como concluídos, ficaram sem pendências;
A27: 2. Os serviços solicitados, porém não executados ou executados parcialmente, tiveram um valor descontado no campo "Resumo do Orçamento dos
A28: Serviços Executados".
A29: 3. O documento deverá ser totalmente preenchido, em todos os campos e sem rasuras. Inutilizar os espaços em branco;
A30: 4. A segunda via do RAT deverá ficar arquivada na dependência beneficiária para consultas futuras;
A31: 5. Deve-se registrar no Portal de Manutenção da DISEC as informações contidas no RAT.
A32: Dúvidas quanto aos itens, quantitativos e valores aplicados aos serviços, deverão ser sanadas com a CONTRATADA durante o atendimento. Caso não
A33: ocorra o esclarecimento, consultar o CESUP SUPRIMENTOS.
A34: Lembramos que o ADMINISTRADOR PREDIAL é o responsável pela fiscalização dos serviços executados na dependência e que a
... A36: dos serviços
B38: ________________________________________________ | H38: ___________________________________________________________________________________
B39: VISTO REPRESENTANTE DA EMPRESA CONTRATADA | H39: CARIMBO E VISTO DA DEPENDÊNCIA
A41: Parecer do Responsável Técnico / Contratada | I41: ENGENHEIRO
I47: CARIMBO - NÚMERO / VISTO DO CREA
A48: O RAT deverá ser emitido em 3 vias, sendo: a 1° Depêndencia Beneficiária, 2° Empresa Contratada, e em 3° CESUP Suprimentos

Sheet Valores
B1: A interessada deverá prrencher os campos em amarelo abaixo.
C3: CONSERVAÇÃO PREDIAL | M3: Informar nos campos em amarelo abaixo o desconto para MA e MO. Poderá ser informado desconto diferente ou igual para MA e MO de forma a ajustar o desconto global ao desconto ofertado na licitação. O campo em verde, após o preenchimento do MA, MO e BDI (em sua respectiva aba), deverá refletir o valor de desconto ofertado na Licitação. O valor efetivo de desconto de MA e MO considerando BDI aparecerá nos campos em Azul.
B4: PROPONENTE : | G4: LOTE: | H4: 03 | M4: Material sem BDI | N4: Mão de obra sem BDI
B5: MAFFENG ENGENHARIA E MANUTENÇÃO LTDA | C5: CNPJ: | D5: 33624704/0001-94 | I5: DESCONTO: | J5: =N7 -> 0.37860761 | M5: 0.3786 | N5: 0.3786 | V5: Não mexer nos dados abaixo. Dados Sem BDI. | AB5: Não mexer nos dados abaixo. Dados com BDI. | AH5: Descontos Calculados
A7: ITEM | C7: QTDE | D7: UN. | E7: UNITÁRIO MATERIAL | F7: UNITÁRIO MÃO DE OBRA | G7: TOTAL UNITÁRIO DO ITEM | H7: TOTAL MATERIAL ROTEIRO | I7: TOTAL MÃO DE OBRA ROTEIRO | J7: TOTAL GERAL ROTEIRO | M7: Desconto Global Calculado com BDI | N7: =1-(J537/AF537) -> 0.37860761 | V7: QTDE | W7: UN. | X7: UNITÁRIO MATERIAL Referência | Y7: UNITÁRIO MÃO DE OBRA Referência | Z7: TOTAL UNITÁRIO DO ITEM Referência | AB7: QTDE | AC7: UN. | AD7: UNITÁRIO MATERIAL Referência | AE7: UNITÁRIO MÃO DE OBRA Referência | AF7: TOTAL UNITÁRIO DO ITEM Referência | AH7: UNITÁRIO MATERIAL Referência | AI7: UNITÁRIO MÃO DE OBRA Referência | AJ7: TOTAL UNITÁRIO DO ITEM Referência
A8: 1 | B8: PRELIMINARES | H8: =SUM(H9:H15) -> 523740.87 | I8: =SUM(I9:I15) -> 204215.58 | J8: =SUM(J9:J15) -> 727956.45 | M8: O valor do campo em verde deverá ser igual ao da proposta apresentada.
A9: 1.1 | B9: Chamado | C9: =V9 -> 286 | D9: =W9 -> un | E9: =ROUND((X9*(1-$M$5))*(1+BDI!$C$21),2) -> 0 | F9: =ROUND((Y9*(1-$N$5))*(1+BDI!$C$21),2) -> 76.34 | G9: =F9+E9 -> 76.34 | H9: =C9*E9 -> 0 | I9: =C9*F9 -> 21833.24 | J9: =SUM(E9:F9)*C9 -> 21833.24 | V9: 286 | W9: un | X9: 0 | Y9: 95.37 | Z9: =SUM(X9:Y9) -> 95.37 | AB9: 286 | AC9: un | AD9: 0 | AE9: 122.86 | AF9: =SUM(AD9:AE9) -> 122.86 | AH9: =IF(E9=0,0,(E9/AD9)-1) -> 0 | AI9: =IF(F9=0,0,(F9/AE9)-1) -> -0.37864236 | AJ9: =IF(G9=0,0,(G9/AF9)-1) -> -0.37864236
A10: 1.2 | B10: Deslocamento | C10: =V10 -> 213840 | D10: =W10 -> km | E10: =ROUND((X10*(1-$M$5))*(1+BDI!$C$21),2) -> 1.51 | F10: =ROUND((Y10*(1-$N$5))*(1+BDI!$C$21),2) -> 0.64 | G10: =F10+E10 -> 2.15 | H10: =C10*E10 -> 322898.4 | I10: =C10*F10 -> 136857.6 | J10: =SUM(E10:F10)*C10 -> 459756 | V10: 213840 | W10: km | X10: 1.89 | Y10: 0.8 | Z10: =SUM(X10:Y10) -> 2.69 | AB10: 213840 | AC10: km | AD10: 2.43 | AE10: 1.03 | AF10: =SUM(AD10:AE10) -> 3.46 | AH10: =IF(E10=0,0,(E10/AD10)-1) -> -0.37860082 | AI10: =IF(F10=0,0,(F10/AE10)-1) -> -0.37864078 | AJ10: =IF(G10=0,0,(G10/AF10)-1) -> -0.37861272
A11: 1.3 | B11: Revisão de instalações | C11: =V11 -> 108 | D11: =W11 -> un | E11: =ROUND((X11*(1-$M$5))*(1+BDI!$C$21),2) -> 79.76 | F11: =ROUND((Y11*(1-$N$5))*(1+BDI!$C$21),2) -> 412.76 | G11: =F11+E11 -> 492.52 | H11: =C11*E11 -> 8614.08 | I11: =C11*F11 -> 44578.08 | J11: =SUM(E11:F11)*C11 -> 53192.16 | V11: 108 | W11: un | X11: 99.64 | Y11: 515.64 | Z11: =SUM(X11:Y11) -> 615.28 | AB11: 108 | AC11: un | AD11: 128.36 | AE11: 664.25 | AF11: =SUM(AD11:AE11) -> 792.61 | AH11: =IF(E11=0,0,(E11/AD11)-1) -> -0.37862262 | AI11: =IF(F11=0,0,(F11/AE11)-1) -> -0.37860745 | AJ11: =IF(G11=0,0,(G11/AF11)-1) -> -0.37860991
A12: 1.4 | B12: Acompanhamento técnico em Segurança do Trabalho | C12: =V12 -> 1 | D12: =W12 -> un | E12: =ROUND((X12*(1-$M$5))*(1+BDI!$C$21),2) -> 0 | F12: =ROUND((Y12*(1-$N$5))*(1+BDI!$C$21),2) -> 389.42 | G12: =F12+E12 -> 389.42 | H12: =C12*E12 -> 0 | I12: =C12*F12 -> 389.42 | J12: =SUM(E12:F12)*C12 -> 389.42 | V12: 1 | W12: un | X12: 0 | Y12: 486.48 | Z12: =SUM(X12:Y12) -> 486.48 | AB12: 1 | AC12: un | AD12: 0 | AE12: 626.68 | AF12: =SUM(AD12:AE12) -> 626.68 | AH12: =IF(E12=0,0,(E12/AD12)-1) -> 0 | AI12: =IF(F12=0,0,(F12/AE12)-1) -> -0.37859833 | AJ12: =IF(G12=0,0,(G12/AF12)-1) -> -0.37859833
A13: 1.5 | B13: Hospedagem de equipe técnica - Serviços prolongados | C13: =V13 -> 108 | D13: =W13 -> un | E13: =ROUND((X13*(1-$M$5))*(1+BDI!$C$21),2) -> 1779.12 | F13: =ROUND((Y13*(1-$N$5))*(1+BDI!$C$21),2) -> 0 | G13: =F13+E13 -> 1779.12 | H13: =C13*E13 -> 192144.96 | I13: =C13*F13 -> 0 | J13: =SUM(E13:F13)*C13 -> 192144.96 | V13: 108 | W13: un | X13: 2222.54 | Y13: 0 | Z13: =SUM(X13:Y13) -> 2222.54 | AB13: 108 | AC13: un | AD13: 2863.08 | AE13: 0 | AF13: =SUM(AD13:AE13) -> 2863.08 | AH13: =IF(E13=0,0,(E13/AD13)-1) -> -0.37859927 | AI13: =IF(F13=0,0,(F13/AE13)-1) -> 0 | AJ13: =IF(G13=0,0,(G13/AF13)-1) -> -0.37859927
A14: 1.6 | B14: Deslocamento Fluvial | C14: =V14 -> 1 | D14: =W14 -> Km | E14: =ROUND((X14*(1-$M$5))*(1+BDI!$C$21),2) -> 0.75 | F14: =ROUND((Y14*(1-$N$5))*(1+BDI!$C$21),2) -> 1.58 | G14: =F14+E14 -> 2.33 | H14: =C14*E14 -> 0.75 | I14: =C14*F14 -> 1.58 | J14: =SUM(E14:F14)*C14 -> 2.33 | M14: Desconto Calculado Material Efetivo | N14: =IF(M5=0,0,ROUND(AH540,4)) -> -0.3786 | V14: 1 | W14: Km | X14: 0.94 | Y14: 1.97 | Z14: =SUM(X14:Y14) -> 2.91 | AB14: 1 | AC14: Km | AD14: 1.21 | AE14: 2.54 | AF14: =SUM(AD14:AE14) -> 3.75 | AH14: =IF(E14=0,0,(E14/AD14)-1) -> -0.38016529 | AI14: =IF(F14=0,0,(F14/AE14)-1) -> -0.37795276 | AJ14: =IF(G14=0,0,(G14/AF14)-1) -> -0.37866667
A15: 1.7 | B15: Laudo técnico fotográfico - Elementos de Sinalização - Padrão BB | C15: =V15 -> 1 | D15: =W15 -> UN | E15: =ROUND((X15*(1-$M$5))*(1+BDI!$C$21),2) -> 82.68 | F15: =ROUND((Y15*(1-$N$5))*(1+BDI!$C$21),2) -> 555.66 | G15: =F15+E15 -> 638.34 | H15: =C15*E15 -> 82.68 | I15: =C15*F15 -> 555.66 | J15: =SUM(E15:F15)*C15 -> 638.34 | M15: Desconto Calculado Mão de Obra Efetivo | N15: =IF(N5=0,0,ROUND(AI540,4)) -> -0.3786 | V15: 1 | W15: UN | X15: 103.29 | Y15: 694.15 | Z15: =SUM(X15:Y15) -> 797.44 | AB15: 1 | AC15: UN | AD15: 133.06 | AE15: 894.2 | AF15: =SUM(AD15:AE15) -> 1027.26 | AH15: =IF(E15=0,0,(E15/AD15)-1) -> -0.37862618 | AI15: =IF(F15=0,0,(F15/AE15)-1) -> -0.37859539 | AJ15: =IF(G15=0,0,(G15/AF15)-1) -> -0.37859938
A16: 2 | B16: IMPLANTAÇÃO / ADMINISTRAÇÃO | H16: =SUM(H17:H52) -> 101208.4 | I16: =SUM(I17:I52) -> 134610.64 | J16: =SUM(J17:J52) -> 235819.04 | M16: Os valores acima consideram o valor informado na aba BDI. | AH16: =IF(E16=0,0,(E16/AD16)-1) -> 0 | AI16: =IF(F16=0,0,(F16/AE16)-1) -> 0 | AJ16: =IF(G16=0,0,(G16/AF16)-1) -> 0
A17: 2.1 | B17: Demolição manual de concreto simples | C17: =V17 -> 24 | D17: =W17 -> m³ | E17: =ROUND((X17*(1-$M$5))*(1+BDI!$C$21),2) -> 0 | F17: =ROUND((Y17*(1-$N$5))*(1+BDI!$C$21),2) -> 306.35 | G17: =F17+E17 -> 306.35 | H17: =C17*E17 -> 0 | I17: =C17*F17 -> 7352.4 | J17: =SUM(E17:F17)*C17 -> 7352.4 | V17: 24 | W17: m³ | X17: 0 | Y17: 382.71 | Z17: =SUM(X17:Y17) -> 382.71 | AB17: 24 | AC17: m³ | AD17: 0 | AE17: 493.01 | AF17: =SUM(AD17:AE17) -> 493.01 | AH17: =IF(E17=0,0,(E17/AD17)-1) -> 0 | AI17: =IF(F17=0,0,(F17/AE17)-1) -> -0.37861301 | AJ17: =IF(G17=0,0,(G17/AF17)-1) -> -0.37861301
A18: 2.2 | B18: Demolição manual de alvenaria de elevação ou elemento vazado, incluindo revestimento | C18: =V18 -> 43 | D18: =W18 -> m³ | E18: =ROUND((X18*(1-$M$5))*(1+BDI!$C$21),2) -> 0 | F18: =ROUND((Y18*(1-$N$5))*(1+BDI!$C$21),2) -> 70.7 | G18: =F18+E18 -> 70.7 | H18: =C18*E18 -> 0 | I18: =C18*F18 -> 3040.1 | J18: =SUM(E18:F18)*C18 -> 3040.1 | M18: A interessada pode alterar o BDI na respectiva aba da planilha eletrônica. A alteração do BDI afeta o desconto calculado efetivo de material e de mão de obra. O valor do BDI deverá ser igual ao da proposta a ser apresentada. | V18: 43 | W18: m³ | X18: 0 | Y18: 88.32 | Z18: =SUM(X18:Y18) -> 88.32 | AB18: 43 | AC18: m³ | AD18: 0 | AE18: 113.77 | AF18: =SUM(AD18:AE18) -> 113.77 | AH18: =IF(E18=0,0,(E18/AD18)-1) -> 0 | AI18: =IF(F18=0,0,(F18/AE18)-1) -> -0.3785708 | AJ18: =IF(G18=0,0,(G18/AF18)-1) -> -0.3785708
A19: 2.3 | B19: Demolição manual de revestimento em massa de parede ou teto ou Dry-Wall | C19: =V19 -> 308 | D19: =W19 -> m³ | E19: =ROUND((X19*(1-$M$5))*(1+BDI!$C$21),2) -> 0 | F19: =ROUND((Y19*(1-$N$5))*(1+BDI!$C$21),2) -> 7.5 | G19: =F19+E19 -> 7.5 | H19: =C19*E19 -> 0 | I19: =C19*F19 -> 2310 | J19: =SUM(E19:F19)*C19 -> 2310 | V19: 308 | W19: m³ | X19: 0 | Y19: 9.37 | Z19: =SUM(X19:Y19) -> 9.37 | AB19: 308 | AC19: m³ | AD19: 0 | AE19: 12.07 | AF19: =SUM(AD19:AE19) -> 12.07 | AH19: =IF(E19=0,0,(E19/AD19)-1) -> 0 | AI19: =IF(F19=0,0,(F19/AE19)-1) -> -0.37862469 | AJ19: =IF(G19=0,0,(G19/AF19)-1) -> -0.37862469
A20: 2.4 | B20: Demolição de pisos em geral (ladrilho hidráulico, camada de enchimento, cerâmica, porcelanato, mármore, granito, pedra e madeira) - Manual | C20: =V20 -> 247 | D20: =W20 -> m² | E20: =ROUND((X20*(1-$M$5))*(1+BDI!$C$21),2) -> 0 | F20: =ROUND((Y20*(1-$N$5))*(1+BDI!$C$21),2) -> 32.99 | G20: =F20+E20 -> 32.99 | H20: =C20*E20 -> 0 | I20: =C20*F20 -> 8148.53 | J20: =SUM(E20:F20)*C20 -> 8148.53 | V20: 247 | W20: m² | X20: 0 | Y20: 41.21 | Z20: =SUM(X20:Y20) -> 41.21 | AB20: 247 | AC20: m² | AD20: 0 | AE20: 53.09 | AF20: =SUM(AD20:AE20) -> 53.09 | AH20: =IF(E20=0,0,(E20/AD20)-1) -> 0 | AI20: =IF(F20=0,0,(F20/AE20)-1) -> -0.37860237 | AJ20: =IF(G20=0,0,(G20/AF20)-1) -> -0.37860237
A21: 2.5 | B21: Demolição de pisos em geral (ladrilho hidráulico, camada de enchimento, cerâmica, porcelanato, mármore, granito, pedra e madeira) - Mecanizado | C21: =V21 -> 96 | D21: =W21 -> m² | E21: =ROUND((X21*(1-$M$5))*(1+BDI!$C$21),2) -> 24.01 | F21: =ROUND((Y21*(1-$N$5))*(1+BDI!$C$21),2) -> 16.5 | G21: =F21+E21 -> 40.51 | H21: =C21*E21 -> 2304.96 | I21: =C21*F21 -> 1584 | J21: =SUM(E21:F21)*C21 -> 3888.96 | V21: 96 | W21: m² | X21: 30 | Y21: 20.61 | Z21: =SUM(X21:Y21) -> 50.61 | AB21: 96 | AC21: m² | AD21: 38.65 | AE21: 26.55 | AF21: =SUM(AD21:AE21) -> 65.2 | AH21: =IF(E21=0,0,(E21/AD21)-1) -> -0.37878396 | AI21: =IF(F21=0,0,(F21/AE21)-1) -> -0.37853107 | AJ21: =IF(G21=0,0,(G21/AF21)-1) -> -0.37868098
A22: 2.6 | B22: Demolição de pavimentação com pré-moldado de concreto ou intertravado | C22: =V22 -> 6 | D22: =W22 -> m² | E22: =ROUND((X22*(1-$M$5))*(1+BDI!$C$21),2) -> 0 | F22: =ROUND((Y22*(1-$N$5))*(1+BDI!$C$21),2) -> 16.5 | G22: =F22+E22 -> 16.5 | H22: =C22*E22 -> 0 | I22: =C22*F22 -> 99 | J22: =SUM(E22:F22)*C22 -> 99 | V22: 6 | W22: m² | X22: 0 | Y22: 20.61 | Z22: =SUM(X22:Y22) -> 20.61 | AB22: 6 | AC22: m² | AD22: 0 | AE22: 26.55 | AF22: =SUM(AD22:AE22) -> 26.55 | AH22: =IF(E22=0,0,(E22/AD22)-1) -> 0 | AI22: =IF(F22=0,0,(F22/AE22)-1) -> -0.37853107 | AJ22: =IF(G22=0,0,(G22/AF22)-1) -> -0.37853107
A23: 2.7 | B23: Demolição de piso cimentado sobre lastro de concreto | C23: =V23 -> 35 | D23: =W23 -> m² | E23: =ROUND((X23*(1-$M$5))*(1+BDI!$C$21),2) -> 0 | F23: =ROUND((Y23*(1-$N$5))*(1+BDI!$C$21),2) -> 30.63 | G23: =F23+E23 -> 30.63 | H23: =C23*E23 -> 0 | I23: =C23*F23 -> 1072.05 | J23: =SUM(E23:F23)*C23 -> 1072.05 | V23: 35 | W23: m² | X23: 0 | Y23: 38.27 | Z23: =SUM(X23:Y23) -> 38.27 | AB23: 35 | AC23: m² | AD23: 0 | AE23: 49.3 | AF23: =SUM(AD23:AE23) -> 49.3 | AH23: =IF(E23=0,0,(E23/AD23)-1) -> 0 | AI23: =IF(F23=0,0,(F23/AE23)-1) -> -0.37870183 | AJ23: =IF(G23=0,0,(G23/AF23)-1) -> -0.37870183
A24: 2.8 | B24: Demolição manual de forro, inclusive sistema de fixação/tarugamento | C24: =V24 -> 794 | D24: =W24 -> m² | E24: =ROUND((X24*(1-$M$5))*(1+BDI!$C$21),2) -> 0 | F24: =ROUND((Y24*(1-$N$5))*(1+BDI!$C$21),2) -> 9.43 | G24: =F24+E24 -> 9.43 | H24: =C24*E24 -> 0 | I24: =C24*F24 -> 7487.42 | J24: =SUM(E24:F24)*C24 -> 7487.42 | M24: A interessada pode utilizar modelo próprio de planilha para cálculo,entretanto,a planilha final a ser apresentada juntamente com a proposta, deverá ter a mesma formatação do orçamento estimado que compõe a licitação. | V24: 794 | W24: m² | X24: 0 | Y24: 11.78 | Z24: =SUM(X24:Y24) -> 11.78 | AB24: 794 | AC24: m² | AD24: 0 | AE24: 15.17 | AF24: =SUM(AD24:AE24) -> 15.17 | AH24: =IF(E24=0,0,(E24/AD24)-1) -> 0 | AI24: =IF(F24=0,0,(F24/AE24)-1) -> -0.37837838 | AJ24: =IF(G24=0,0,(G24/AF24)-1) -> -0.37837838
A25: 2.9 | B25: Demolição de contrapiso/argamassa regularizante, isolante ou protetora | C25: =V25 -> 172 | D25: =W25 -> m² | E25: =ROUND((X25*(1-$M$5))*(1+BDI!$C$21),2) -> 0 | F25: =ROUND((Y25*(1-$N$5))*(1+BDI!$C$21),2) -> 11.78 | G25: =F25+E25 -> 11.78 | H25: =C25*E25 -> 0 | I25: =C25*F25 -> 2026.16 | J25: =SUM(E25:F25)*C25 -> 2026.16 | V25: 172 | W25: m² | X25: 0 | Y25: 14.72 | Z25: =SUM(X25:Y25) -> 14.72 | AB25: 172 | AC25: m² | AD25: 0 | AE25: 18.96 | AF25: =SUM(AD25:AE25) -> 18.96 | AH25: =IF(E25=0,0,(E25/AD25)-1) -> 0 | AI25: =IF(F25=0,0,(F25/AE25)-1) -> -0.37869198 | AJ25: =IF(G25=0,0,(G25/AF25)-1) -> -0.37869198
A26: 2.10 | B26: Demolição de estrutura em madeira para telhado | C26: =V26 -> 52 | D26: =W26 -> m² | E26: =ROUND((X26*(1-$M$5))*(1+BDI!$C$21),2) -> 0 | F26: =ROUND((Y26*(1-$N$5))*(1+BDI!$C$21),2) -> 32.56 | G26: =F26+E26 -> 32.56 | H26: =C26*E26 -> 0 | I26: =C26*F26 -> 1693.12 | J26: =SUM(E26:F26)*C26 -> 1693.12 | V26: 52 | W26: m² | X26: 0 | Y26: 40.68 | Z26: =SUM(X26:Y26) -> 40.68 | AB26: 52 | AC26: m² | AD26: 0 | AE26: 52.4 | AF26: =SUM(AD26:AE26) -> 52.4 | AH26: =IF(E26=0,0,(E26/AD26)-1) -> 0 | AI26: =IF(F26=0,0,(F26/AE26)-1) -> -0.37862595 | AJ26: =IF(G26=0,0,(G26/AF26)-1) -> -0.37862595
A27: 2.11 | B27: Retirada de cumeeira, espigão, rufo, calha ou chapim, perfil qualquer | C27: =V27 -> 137 | D27: =W27 -> m | E27: =ROUND((X27*(1-$M$5))*(1+BDI!$C$21),2) -> 0 | F27: =ROUND((Y27*(1-$N$5))*(1+BDI!$C$21),2) -> 15.21 | G27: =F27+E27 -> 15.21 | H27: =C27*E27 -> 0 | I27: =C27*F27 -> 2083.77 | J27: =SUM(E27:F27)*C27 -> 2083.77 | V27: 137 | W27: m | X27: 0 | Y27: 19 | Z27: =SUM(X27:Y27) -> 19 | AB27: 137 | AC27: m | AD27: 0 | AE27: 24.48 | AF27: =SUM(AD27:AE27) -> 24.48 | AH27: =IF(E27=0,0,(E27/AD27)-1) -> 0 | AI27: =IF(F27=0,0,(F27/AE27)-1) -> -0.37867647 | AJ27: =IF(G27=0,0,(G27/AF27)-1) -> -0.37867647
A28: 2.12 | B28: Retirada de piso tátil com limpeza | C28: =V28 -> 564 | D28: =W28 -> m² | E28: =ROUND((X28*(1-$M$5))*(1+BDI!$C$21),2) -> 10.11 | F28: =ROUND((Y28*(1-$N$5))*(1+BDI!$C$21),2) -> 24.78 | G28: =F28+E28 -> 34.89 | H28: =C28*E28 -> 5702.04 | I28: =C28*F28 -> 13975.92 | J28: =SUM(E28:F28)*C28 -> 19677.96 | V28: 564 | W28: m² | X28: 12.63 | Y28: 30.95 | Z28: =SUM(X28:Y28) -> 43.58 | AB28: 564 | AC28: m² | AD28: 16.27 | AE28: 39.87 | AF28: =SUM(AD28:AE28) -> 56.14 | AH28: =IF(E28=0,0,(E28/AD28)-1) -> -0.37861094 | AI28: =IF(F28=0,0,(F28/AE28)-1) -> -0.37848006 | AJ28: =IF(G28=0,0,(G28/AF28)-1) -> -0.37851799
A29: 2.13 | B29: Remoção de revestimento de piso de carpete ou manta vinílica | C29: =V29 -> 1626 | D29: =W29 -> m² | E29: =ROUND((X29*(1-$M$5))*(1+BDI!$C$21),2) -> 10.11 | F29: =ROUND((Y29*(1-$N$5))*(1+BDI!$C$21),2) -> 12.54 | G29: =F29+E29 -> 22.65 | H29: =C29*E29 -> 16438.86 | I29: =C29*F29 -> 20390.04 | J29: =SUM(E29:F29)*C29 -> 36828.9 | V29: 1626 | W29: m² | X29: 12.63 | Y29: 15.66 | Z29: =SUM(X29:Y29) -> 28.29 | AB29: 1626 | AC29: m² | AD29: 16.27 | AE29: 20.17 | AF29: =SUM(AD29:AE29) -> 36.44 | AH29: =IF(E29=0,0,(E29/AD29)-1) -> -0.37861094 | AI29: =IF(F29=0,0,(F29/AE29)-1) -> -0.37828458 | AJ29: =IF(G29=0,0,(G29/AF29)-1) -> -0.3784303
A30: 2.14 | B30: Ajuste de Piso Elevado (remoção e recolocação de revestimentos e placas do piso inclusive) | C30: =V30 -> 49 | D30: =W30 -> m² | E30: =ROUND((X30*(1-$M$5))*(1+BDI!$C$21),2) -> 7.18 | F30: =ROUND((Y30*(1-$N$5))*(1+BDI!$C$21),2) -> 65.25 | G30: =F30+E30 -> 72.43 | H30: =C30*E30 -> 351.82 | I30: =C30*F30 -> 3197.25 | J30: =SUM(E30:F30)*C30 -> 3549.07 | V30: 49 | W30: m² | X30: 8.97 | Y30: 81.51 | Z30: =SUM(X30:Y30) -> 90.48 | AB30: 49 | AC30: m² | AD30: 11.56 | AE30: 105 | AF30: =SUM(AD30:AE30) -> 116.56 | AH30: =IF(E30=0,0,(E30/AD30)-1) -> -0.37889273 | AI30: =IF(F30=0,0,(F30/AE30)-1) -> -0.37857143 | AJ30: =IF(G30=0,0,(G30/AF30)-1) -> -0.37860329
A31: 2.15 | B31: Retirada de piso elevado, inclusive estrutura de sustentação | C31: =V31 -> 153 | D31: =W31 -> m² | E31: =ROUND((X31*(1-$M$5))*(1+BDI!$C$21),2) -> 0 | F31: =ROUND((Y31*(1-$N$5))*(1+BDI!$C$21),2) -> 30.06 | G31: =F31+E31 -> 30.06 | H31: =C31*E31 -> 0 | I31: =C31*F31 -> 4599.18 | J31: =SUM(E31:F31)*C31 -> 4599.18 | V31: 153 | W31: m² | X31: 0 | Y31: 37.55 | Z31: =SUM(X31:Y31) -> 37.55 | AB31: 153 | AC31: m² | AD31: 0 | AE31: 48.37 | AF31: =SUM(AD31:AE31) -> 48.37 | AH31: =IF(E31=0,0,(E31/AD31)-1) -> 0 | AI31: =IF(F31=0,0,(F31/AE31)-1) -> -0.37854042 | AJ31: =IF(G31=0,0,(G31/AF31)-1) -> -0.37854042
A32: 2.16 | B32: Reinstalação de piso elevado proveniente de reaproveitamento, incluso material | C32: =V32 -> 12 | D32: =W32 -> m² | E32: =ROUND((X32*(1-$M$5))*(1+BDI!$C$21),2) -> 1.42 | F32: =ROUND((Y32*(1-$N$5))*(1+BDI!$C$21),2) -> 70.72 | G32: =F32+E32 -> 72.14 | H32: =C32*E32 -> 17.04 | I32: =C32*F32 -> 848.64 | J32: =SUM(E32:F32)*C32 -> 865.68 | V32: 12 | W32: m² | X32: 1.77 | Y32: 88.35 | Z32: =SUM(X32:Y32) -> 90.12 | AB32: 12 | AC32: m² | AD32: 2.28 | AE32: 113.81 | AF32: =SUM(AD32:AE32) -> 116.09 | AH32: =IF(E32=0,0,(E32/AD32)-1) -> -0.37719298 | AI32: =IF(F32=0,0,(F32/AE32)-1) -> -0.37861348 | AJ32: =IF(G32=0,0,(G32/AF32)-1) -> -0.37858558
A33: 2.17 | B33: Retirada ou recolocação de vidro | C33: =V33 -> 358 | D33: =W33 -> m² | E33: =ROUND((X33*(1-$M$5))*(1+BDI!$C$21),2) -> 10.33 | F33: =ROUND((Y33*(1-$N$5))*(1+BDI!$C$21),2) -> 16.84 | G33: =F33+E33 -> 27.17 | H33: =C33*E33 -> 3698.14 | I33: =C33*F33 -> 6028.72 | J33: =SUM(E33:F33)*C33 -> 9726.86 | V33: 358 | W33: m² | X33: 12.9 | Y33: 21.04 | Z33: =SUM(X33:Y33) -> 33.94 | AB33: 358 | AC33: m² | AD33: 16.62 | AE33: 27.1 | AF33: =SUM(AD33:AE33) -> 43.72 | AH33: =IF(E33=0,0,(E33/AD33)-1) -> -0.37845969 | AI33: =IF(F33=0,0,(F33/AE33)-1) -> -0.37859779 | AJ33: =IF(G33=0,0,(G33/AF33)-1) -> -0.37854529
A34: 2.18 | B34: Remoção de entulho com caçamba metálica, inclusive limpeza, transporte, carga, descarga e descarte conforme legislação ambiental - Material de descarte (alvenaria, estruturas metálicas, madeiramento, revestimentos cerâmicos, gesso, dry-wall, entre outros) | C34: =V34 -> 694 | D34: =W34 -> m³ | E34: =ROUND((X34*(1-$M$5))*(1+BDI!$C$21),2) -> 50.35 | F34: =ROUND((Y34*(1-$N$5))*(1+BDI!$C$21),2) -> 14.8 | G34: =F34+E34 -> 65.15 | H34: =C34*E34 -> 34942.9 | I34: =C34*F34 -> 10271.2 | J34: =SUM(E34:F34)*C34 -> 45214.1 | V34: 694 | W34: m³ | X34: 62.9 | Y34: 18.49 | Z34: =SUM(X34:Y34) -> 81.39 | AB34: 694 | AC34: m³ | AD34: 81.03 | AE34: 23.82 | AF34: =SUM(AD34:AE34) -> 104.85 | AH34: =IF(E34=0,0,(E34/AD34)-1) -> -0.3786252 | AI34: =IF(F34=0,0,(F34/AE34)-1) -> -0.37867338 | AJ34: =IF(G34=0,0,(G34/AF34)-1) -> -0.37863615
A35: 2.19 | B35: Remoção / Remanejamento de placa aérea | C35: =V35 -> 150 | D35: =W35 -> un | E35: =ROUND((X35*(1-$M$5))*(1+BDI!$C$21),2) -> 3.14 | F35: =ROUND((Y35*(1-$N$5))*(1+BDI!$C$21),2) -> 45.55 | G35: =F35+E35 -> 48.69 | H35: =C35*E35 -> 471 | I35: =C35*F35 -> 6832.5 | J35: =SUM(E35:F35)*C35 -> 7303.5 | V35: 150 | W35: un | X35: 3.92 | Y35: 56.9 | Z35: =SUM(X35:Y35) -> 60.82 | AB35: 150 | AC35: un | AD35: 5.05 | AE35: 73.3 | AF35: =SUM(AD35:AE35) -> 78.35 | AH35: =IF(E35=0,0,(E35/AD35)-1) -> -0.37821782 | AI35: =IF(F35=0,0,(F35/AE35)-1) -> -0.37858117 | AJ35: =IF(G35=0,0,(G35/AF35)-1) -> -0.37855775
A36: 2.20 | B36: Andaime tubular fachadeiro | C36: =V36 -> 202 | D36: =W36 -> m²/mês | E36: =ROUND((X36*(1-$M$5))*(1+BDI!$C$21),2) -> 17.31 | F36: =ROUND((Y36*(1-$N$5))*(1+BDI!$C$21),2) -> 7.34 | G36: =F36+E36 -> 24.65 | H36: =C36*E36 -> 3496.62 | I36: =C36*F36 -> 1482.68 | J36: =SUM(E36:F36)*C36 -> 4979.3 | V36: 202 | W36: m²/mês | X36: 21.63 | Y36: 9.17 | Z36: =SUM(X36:Y36) -> 30.8 | AB36: 202 | AC36: m²/mês | AD36: 27.86 | AE36: 11.81 | AF36: =SUM(AD36:AE36) -> 39.67 | AH36: =IF(E36=0,0,(E36/AD36)-1) -> -0.37867911 | AI36: =IF(F36=0,0,(F36/AE36)-1) -> -0.3784928 | AJ36: =IF(G36=0,0,(G36/AF36)-1) -> -0.37862365
... A52: 2.36 | B52: Tela para Andaime | C52: =V52 -> 1 | D52: =W52 -> m² | E52: =ROUND((X52*(1-$M$5))*(1+BDI!$C$21),2) -> 2.1 | F52: =ROUND((Y52*(1-$N$5))*(1+BDI!$C$21),2) -> 3.34 | G52: =F52+E52 -> 5.44 | H52: =C52*E52 -> 2.1 | I52: =C52*F52 -> 3.34 | J52: =SUM(E52:F52)*C52 -> 5.44 | V52: 1 | W52: m² | X52: 2.62 | Y52: 4.17 | Z52: =SUM(X52:Y52) -> 6.79 | AB52: 1 | AC52: m² | AD52: 3.38 | AE52: 5.37 | AF52: =SUM(AD52:AE52) -> 8.75 | AH52: =IF(E52=0,0,(E52/AD52)-1) -> -0.37869822 | AI52: =IF(F52=0,0,(F52/AE52)-1) -> -0.37802607 | AJ52: =IF(G52=0,0,(G52/AF52)-1) -> -0.37828571
A53: 3 | B53: MOVIMENTO DE TERRA | H53: =SUM(H54:H55) -> 1.89 | I53: =SUM(I54:I55) -> 103.23 | J53: =SUM(J54:J55) -> 105.12 | AH53: =IF(E53=0,0,(E53/AD53)-1) -> 0 | AI53: =IF(F53=0,0,(F53/AE53)-1) -> 0 | AJ53: =IF(G53=0,0,(G53/AF53)-1) -> 0
A54: 3.1 | B54: Escavação Manual em Solo | C54: =V54 -> 1 | D54: =W54 -> m³ | E54: =ROUND((X54*(1-$M$5))*(1+BDI!$C$21),2) -> 0 | F54: =ROUND((Y54*(1-$N$5))*(1+BDI!$C$21),2) -> 84.6 | G54: =F54+E54 -> 84.6 | H54: =C54*E54 -> 0 | I54: =C54*F54 -> 84.6 | J54: =SUM(E54:F54)*C54 -> 84.6 | V54: 1 | W54: m³ | X54: 0 | Y54: 105.68 | Z54: =SUM(X54:Y54) -> 105.68 | AB54: 1 | AC54: m³ | AD54: 0 | AE54: 136.14 | AF54: =SUM(AD54:AE54) -> 136.14 | AH54: =IF(E54=0,0,(E54/AD54)-1) -> 0 | AI54: =IF(F54=0,0,(F54/AE54)-1) -> -0.37858087 | AJ54: =IF(G54=0,0,(G54/AF54)-1) -> -0.37858087
A55: 3.2 | B55: Reaterro/Aterro Manual de Solo | C55: =V55 -> 1 | D55: =W55 -> m³ | E55: =ROUND((X55*(1-$M$5))*(1+BDI!$C$21),2) -> 1.89 | F55: =ROUND((Y55*(1-$N$5))*(1+BDI!$C$21),2) -> 18.63 | G55: =F55+E55 -> 20.52 | H55: =C55*E55 -> 1.89 | I55: =C55*F55 -> 18.63 | J55: =SUM(E55:F55)*C55 -> 20.52 | V55: 1 | W55: m³ | X55: 2.36 | Y55: 23.27 | Z55: =SUM(X55:Y55) -> 25.63 | AB55: 1 | AC55: m³ | AD55: 3.04 | AE55: 29.98 | AF55: =SUM(AD55:AE55) -> 33.02 | AH55: =IF(E55=0,0,(E55/AD55)-1) -> -0.37828947 | AI55: =IF(F55=0,0,(F55/AE55)-1) -> -0.37858572 | AJ55: =IF(G55=0,0,(G55/AF55)-1) -> -0.37855845
A56: 4 | B56: FUNDAÇÃO | H56: 0 | I56: 0 | J56: 0 | AH56: =IF(E56=0,0,(E56/AD56)-1) -> 0 | AI56: =IF(F56=0,0,(F56/AE56)-1) -> 0 | AJ56: =IF(G56=0,0,(G56/AF56)-1) -> 0
A57: 5 | B57: ESTRUTURA | H57: =SUM(H58:H61) -> 10931.85 | I57: =SUM(I58:I61) -> 3863.51 | J57: =SUM(J58:J61) -> 14795.36 | AH57: =IF(E57=0,0,(E57/AD57)-1) -> 0 | AI57: =IF(F57=0,0,(F57/AE57)-1) -> 0 | AJ57: =IF(G57=0,0,(G57/AF57)-1) -> 0
A58: 5.1 | B58: Base de concreto para fixação de TAA/TTE | C58: =V58 -> 6 | D58: =W58 -> m³ | E58: =ROUND((X58*(1-$M$5))*(1+BDI!$C$21),2) -> 644.99 | F58: =ROUND((Y58*(1-$N$5))*(1+BDI!$C$21),2) -> 58.24 | G58: =F58+E58 -> 703.23 | H58: =C58*E58 -> 3869.94 | I58: =C58*F58 -> 349.44 | J58: =SUM(E58:F58)*C58 -> 4219.38 | V58: 6 | W58: m³ | X58: 805.75 | Y58: 72.75 | Z58: =SUM(X58:Y58) -> 878.5 | AB58: 6 | AC58: m³ | AD58: 1037.97 | AE58: 93.72 | AF58: =SUM(AD58:AE58) -> 1131.69 | AH58: =IF(E58=0,0,(E58/AD58)-1) -> -0.37860439 | AI58: =IF(F58=0,0,(F58/AE58)-1) -> -0.37857448 | AJ58: =IF(G58=0,0,(G58/AF58)-1) -> -0.37860191
A59: 5.2 | B59: Montagem e Desmontagem de escoramento em madeira. | C59: =V59 -> 22 | D59: =W59 -> m² | E59: =ROUND((X59*(1-$M$5))*(1+BDI!$C$21),2) -> 121.32 | F59: =ROUND((Y59*(1-$N$5))*(1+BDI!$C$21),2) -> 57.34 | G59: =F59+E59 -> 178.66 | H59: =C59*E59 -> 2669.04 | I59: =C59*F59 -> 1261.48 | J59: =SUM(E59:F59)*C59 -> 3930.52 | V59: 22 | W59: m² | X59: 151.56 | Y59: 71.63 | Z59: =SUM(X59:Y59) -> 223.19 | AB59: 22 | AC59: m² | AD59: 195.24 | AE59: 92.27 | AF59: =SUM(AD59:AE59) -> 287.51 | AH59: =IF(E59=0,0,(E59/AD59)-1) -> -0.37861094 | AI59: =IF(F59=0,0,(F59/AE59)-1) -> -0.37856291 | AJ59: =IF(G59=0,0,(G59/AF59)-1) -> -0.37859553
A60: 5.3 | B60: Montagem e Desmontagem de escoramento metálico. | C60: =V60 -> 19 | D60: =W60 -> m² | E60: =ROUND((X60*(1-$M$5))*(1+BDI!$C$21),2) -> 89.13 | F60: =ROUND((Y60*(1-$N$5))*(1+BDI!$C$21),2) -> 49.57 | G60: =F60+E60 -> 138.7 | H60: =C60*E60 -> 1693.47 | I60: =C60*F60 -> 941.83 | J60: =SUM(E60:F60)*C60 -> 2635.3 | V60: 19 | W60: m² | X60: 111.35 | Y60: 61.92 | Z60: =SUM(X60:Y60) -> 173.27 | AB60: 19 | AC60: m² | AD60: 143.44 | AE60: 79.77 | AF60: =SUM(AD60:AE60) -> 223.21 | AH60: =IF(E60=0,0,(E60/AD60)-1) -> -0.37862521 | AI60: =IF(F60=0,0,(F60/AE60)-1) -> -0.37858844 | AJ60: =IF(G60=0,0,(G60/AF60)-1) -> -0.37861207
A61: 5.4 | B61: Concreto fck = 15 MPa, controle tipo "B", e = 10 cm, e armado com tela de aço CA-60 | C61: =V61 -> 44 | D61: =W61 -> m² | E61: =ROUND((X61*(1-$M$5))*(1+BDI!$C$21),2) -> 61.35 | F61: =ROUND((Y61*(1-$N$5))*(1+BDI!$C$21),2) -> 29.79 | G61: =F61+E61 -> 91.14 | H61: =C61*E61 -> 2699.4 | I61: =C61*F61 -> 1310.76 | J61: =SUM(E61:F61)*C61 -> 4010.16 | V61: 44 | W61: m² | X61: 76.64 | Y61: 37.21 | Z61: =SUM(X61:Y61) -> 113.85 | AB61: 44 | AC61: m² | AD61: 98.73 | AE61: 47.93 | AF61: =SUM(AD61:AE61) -> 146.66 | AH61: =IF(E61=0,0,(E61/AD61)-1) -> -0.37860833 | AI61: =IF(F61=0,0,(F61/AE61)-1) -> -0.3784686 | AJ61: =IF(G61=0,0,(G61/AF61)-1) -> -0.37856266
A62: 6 | B62: ALVENARIAS E OUTRAS VEDAÇÕES | H62: =SUM(H63:H65) -> 15860.15 | I62: =SUM(I63:I65) -> 6694.66 | J62: =SUM(J63:J65) -> 22554.81 | AH62: =IF(E62=0,0,(E62/AD62)-1) -> 0 | AI62: =IF(F62=0,0,(F62/AE62)-1) -> 0 | AJ62: =IF(G62=0,0,(G62/AF62)-1) -> 0
A63: 6.1 | B63: Alvenaria com tijolo cerâmico furado | C63: =V63 -> 87 | D63: =W63 -> m² | E63: =ROUND((X63*(1-$M$5))*(1+BDI!$C$21),2) -> 23.09 | F63: =ROUND((Y63*(1-$N$5))*(1+BDI!$C$21),2) -> 41.66 | G63: =F63+E63 -> 64.75 | H63: =C63*E63 -> 2008.83 | I63: =C63*F63 -> 3624.42 | J63: =SUM(E63:F63)*C63 -> 5633.25 | V63: 87 | W63: m² | X63: 28.84 | Y63: 52.04 | Z63: =SUM(X63:Y63) -> 80.88 | AB63: 87 | AC63: m² | AD63: 37.15 | AE63: 67.04 | AF63: =SUM(AD63:AE63) -> 104.19 | AH63: =IF(E63=0,0,(E63/AD63)-1) -> -0.37846568 | AI63: =IF(F63=0,0,(F63/AE63)-1) -> -0.37857995 | AJ63: =IF(G63=0,0,(G63/AF63)-1) -> -0.37853921
A64: 6.2 | B64: Parede de gesso em placas duplas acartonado dry wall - inclusive para ambientes úmidos - RU | C64: =V64 -> 116 | D64: =W64 -> m² | E64: =ROUND((X64*(1-$M$5))*(1+BDI!$C$21),2) -> 109.66 | F64: =ROUND((Y64*(1-$N$5))*(1+BDI!$C$21),2) -> 12.53 | G64: =F64+E64 -> 122.19 | H64: =C64*E64 -> 12720.56 | I64: =C64*F64 -> 1453.48 | J64: =SUM(E64:F64)*C64 -> 14174.04 | V64: 116 | W64: m² | X64: 136.99 | Y64: 15.65 | Z64: =SUM(X64:Y64) -> 152.64 | AB64: 116 | AC64: m² | AD64: 176.47 | AE64: 20.16 | AF64: =SUM(AD64:AE64) -> 196.63 | AH64: =IF(E64=0,0,(E64/AD64)-1) -> -0.37859126 | AI64: =IF(F64=0,0,(F64/AE64)-1) -> -0.37847222 | AJ64: =IF(G64=0,0,(G64/AF64)-1) -> -0.37857906
A65: 6.3 | B65: Rasgo e fechamento em alvenaria e piso | C65: =V65 -> 54 | D65: =W65 -> m | E65: =ROUND((X65*(1-$M$5))*(1+BDI!$C$21),2) -> 20.94 | F65: =ROUND((Y65*(1-$N$5))*(1+BDI!$C$21),2) -> 29.94 | G65: =F65+E65 -> 50.88 | H65: =C65*E65 -> 1130.76 | I65: =C65*F65 -> 1616.76 | J65: =SUM(E65:F65)*C65 -> 2747.52 | V65: 54 | W65: m | X65: 26.16 | Y65: 37.4 | Z65: =SUM(X65:Y65) -> 63.56 | AB65: 54 | AC65: m | AD65: 33.7 | AE65: 48.18 | AF65: =SUM(AD65:AE65) -> 81.88 | AH65: =IF(E65=0,0,(E65/AD65)-1) -> -0.37863501 | AI65: =IF(F65=0,0,(F65/AE65)-1) -> -0.37858032 | AJ65: =IF(G65=0,0,(G65/AF65)-1) -> -0.37860283
A66: 7 | B66: COBERTURA | H66: =SUM(H67:H81) -> 41755.25 | I66: =SUM(I67:I81) -> 15352.5 | J66: =SUM(J67:J81) -> 57107.75 | AH66: =IF(E66=0,0,(E66/AD66)-1) -> 0 | AI66: =IF(F66=0,0,(F66/AE66)-1) -> 0 | AJ66: =IF(G66=0,0,(G66/AF66)-1) -> 0
A67: 7.1 | B67: Cobertura com telha de alumínio envernizada ou pintada, e=0,5 mm | C67: =V67 -> 185 | D67: =W67 -> m² | E67: =ROUND((X67*(1-$M$5))*(1+BDI!$C$21),2) -> 70.98 | F67: =ROUND((Y67*(1-$N$5))*(1+BDI!$C$21),2) -> 12.8 | G67: =F67+E67 -> 83.78 | H67: =C67*E67 -> 13131.3 | I67: =C67*F67 -> 2368 | J67: =SUM(E67:F67)*C67 -> 15499.3 | V67: 185 | W67: m² | X67: 88.67 | Y67: 15.99 | Z67: =SUM(X67:Y67) -> 104.66 | AB67: 185 | AC67: m² | AD67: 114.22 | AE67: 20.6 | AF67: =SUM(AD67:AE67) -> 134.82 | AH67: =IF(E67=0,0,(E67/AD67)-1) -> -0.37856768 | AI67: =IF(F67=0,0,(F67/AE67)-1) -> -0.37864078 | AJ67: =IF(G67=0,0,(G67/AF67)-1) -> -0.37857885
A68: 7.2 | B68: Cobertura em telha com isolamento termoacustico em espuma rígida de poliuretano (PU) injetado | C68: =V68 -> 8 | D68: =W68 -> m² | E68: =ROUND((X68*(1-$M$5))*(1+BDI!$C$21),2) -> 136.41 | F68: =ROUND((Y68*(1-$N$5))*(1+BDI!$C$21),2) -> 10.24 | G68: =F68+E68 -> 146.65 | H68: =C68*E68 -> 1091.28 | I68: =C68*F68 -> 81.92 | J68: =SUM(E68:F68)*C68 -> 1173.2 | V68: 8 | W68: m² | X68: 170.41 | Y68: 12.79 | Z68: =SUM(X68:Y68) -> 183.2 | AB68: 8 | AC68: m² | AD68: 219.52 | AE68: 16.48 | AF68: =SUM(AD68:AE68) -> 236 | AH68: =IF(E68=0,0,(E68/AD68)-1) -> -0.37859876 | AI68: =IF(F68=0,0,(F68/AE68)-1) -> -0.37864078 | AJ68: =IF(G68=0,0,(G68/AF68)-1) -> -0.37860169
A69: 7.3 | B69: Cumeeira em chapa metálica | C69: =V69 -> 1 | D69: =W69 -> m | E69: =ROUND((X69*(1-$M$5))*(1+BDI!$C$21),2) -> 100.57 | F69: =ROUND((Y69*(1-$N$5))*(1+BDI!$C$21),2) -> 5.59 | G69: =F69+E69 -> 106.16 | H69: =C69*E69 -> 100.57 | I69: =C69*F69 -> 5.59 | J69: =SUM(E69:F69)*C69 -> 106.16 | V69: 1 | W69: m | X69: 125.64 | Y69: 6.98 | Z69: =SUM(X69:Y69) -> 132.62 | AB69: 1 | AC69: m | AD69: 161.85 | AE69: 8.99 | AF69: =SUM(AD69:AE69) -> 170.84 | AH69: =IF(E69=0,0,(E69/AD69)-1) -> -0.37862218 | AI69: =IF(F69=0,0,(F69/AE69)-1) -> -0.378198 | AJ69: =IF(G69=0,0,(G69/AF69)-1) -> -0.37859986
A70: 7.4 | B70: Cobertura com telha cerâmica, incluso transporte vertical | C70: =V70 -> 22 | D70: =W70 -> m² | E70: =ROUND((X70*(1-$M$5))*(1+BDI!$C$21),2) -> 41.57 | F70: =ROUND((Y70*(1-$N$5))*(1+BDI!$C$21),2) -> 11.01 | G70: =F70+E70 -> 52.58 | H70: =C70*E70 -> 914.54 | I70: =C70*F70 -> 242.22 | J70: =SUM(E70:F70)*C70 -> 1156.76 | V70: 22 | W70: m² | X70: 51.93 | Y70: 13.76 | Z70: =SUM(X70:Y70) -> 65.69 | AB70: 22 | AC70: m² | AD70: 66.9 | AE70: 17.73 | AF70: =SUM(AD70:AE70) -> 84.63 | AH70: =IF(E70=0,0,(E70/AD70)-1) -> -0.37862481 | AI70: =IF(F70=0,0,(F70/AE70)-1) -> -0.37901861 | AJ70: =IF(G70=0,0,(G70/AF70)-1) -> -0.37870731
A71: 7.5 | B71: Cumeeira para telha cerâmica emboçada com argamassa | C71: =V71 -> 8 | D71: =W71 -> m | E71: =ROUND((X71*(1-$M$5))*(1+BDI!$C$21),2) -> 17.42 | F71: =ROUND((Y71*(1-$N$5))*(1+BDI!$C$21),2) -> 23.72 | G71: =F71+E71 -> 41.14 | H71: =C71*E71 -> 139.36 | I71: =C71*F71 -> 189.76 | J71: =SUM(E71:F71)*C71 -> 329.12 | V71: 8 | W71: m | X71: 21.76 | Y71: 29.63 | Z71: =SUM(X71:Y71) -> 51.39 | AB71: 8 | AC71: m | AD71: 28.03 | AE71: 38.17 | AF71: =SUM(AD71:AE71) -> 66.2 | AH71: =IF(E71=0,0,(E71/AD71)-1) -> -0.37852301 | AI71: =IF(F71=0,0,(F71/AE71)-1) -> -0.37856956 | AJ71: =IF(G71=0,0,(G71/AF71)-1) -> -0.37854985
A72: 7.6 | B72: Cumeeira universal para telhado de fibrocimento, e=6mm | C72: =V72 -> 40 | D72: =W72 -> m | E72: =ROUND((X72*(1-$M$5))*(1+BDI!$C$21),2) -> 58.68 | F72: =ROUND((Y72*(1-$N$5))*(1+BDI!$C$21),2) -> 26.74 | G72: =F72+E72 -> 85.42 | H72: =C72*E72 -> 2347.2 | I72: =C72*F72 -> 1069.6 | J72: =SUM(E72:F72)*C72 -> 3416.8 | V72: 40 | W72: m | X72: 73.3 | Y72: 33.41 | Z72: =SUM(X72:Y72) -> 106.71 | AB72: 40 | AC72: m | AD72: 94.43 | AE72: 43.04 | AF72: =SUM(AD72:AE72) -> 137.47 | AH72: =IF(E72=0,0,(E72/AD72)-1) -> -0.37858731 | AI72: =IF(F72=0,0,(F72/AE72)-1) -> -0.37871747 | AJ72: =IF(G72=0,0,(G72/AF72)-1) -> -0.37862806
A73: 7.7 | B73: Cobertura com telha de fibrocimento, e = 6 mm, | C73: =V73 -> 173 | D73: =W73 -> m² | E73: =ROUND((X73*(1-$M$5))*(1+BDI!$C$21),2) -> 31.64 | F73: =ROUND((Y73*(1-$N$5))*(1+BDI!$C$21),2) -> 6.82 | G73: =F73+E73 -> 38.46 | H73: =C73*E73 -> 5473.72 | I73: =C73*F73 -> 1179.86 | J73: =SUM(E73:F73)*C73 -> 6653.58 | V73: 173 | W73: m² | X73: 39.53 | Y73: 8.52 | Z73: =SUM(X73:Y73) -> 48.05 | AB73: 173 | AC73: m² | AD73: 50.92 | AE73: 10.98 | AF73: =SUM(AD73:AE73) -> 61.9 | AH73: =IF(E73=0,0,(E73/AD73)-1) -> -0.37863315 | AI73: =IF(F73=0,0,(F73/AE73)-1) -> -0.37887067 | AJ73: =IF(G73=0,0,(G73/AF73)-1) -> -0.37867528
A74: 7.8 | B74: Calha de chapa galvanizada nº 24 desenvolvimento 33 cm | C74: =V74 -> 98 | D74: =W74 -> m | E74: =ROUND((X74*(1-$M$5))*(1+BDI!$C$21),2) -> 40.7 | F74: =ROUND((Y74*(1-$N$5))*(1+BDI!$C$21),2) -> 10.88 | G74: =F74+E74 -> 51.58 | H74: =C74*E74 -> 3988.6 | I74: =C74*F74 -> 1066.24 | J74: =SUM(E74:F74)*C74 -> 5054.84 | V74: 98 | W74: m | X74: 50.85 | Y74: 13.59 | Z74: =SUM(X74:Y74) -> 64.44 | AB74: 98 | AC74: m | AD74: 65.5 | AE74: 17.51 | AF74: =SUM(AD74:AE74) -> 83.01 | AH74: =IF(E74=0,0,(E74/AD74)-1) -> -0.37862595 | AI74: =IF(F74=0,0,(F74/AE74)-1) -> -0.37864078 | AJ74: =IF(G74=0,0,(G74/AF74)-1) -> -0.37862908
A75: 7.9 | B75: Rufo de chapa de aço galvanizado com desenvolvimento até 50 cm | C75: =V75 -> 65 | D75: =W75 -> m | E75: =ROUND((X75*(1-$M$5))*(1+BDI!$C$21),2) -> 35.61 | F75: =ROUND((Y75*(1-$N$5))*(1+BDI!$C$21),2) -> 7.36 | G75: =F75+E75 -> 42.97 | H75: =C75*E75 -> 2314.65 | I75: =C75*F75 -> 478.4 | J75: =SUM(E75:F75)*C75 -> 2793.05 | V75: 65 | W75: m | X75: 44.48 | Y75: 9.2 | Z75: =SUM(X75:Y75) -> 53.68 | AB75: 65 | AC75: m | AD75: 57.3 | AE75: 11.85 | AF75: =SUM(AD75:AE75) -> 69.15 | AH75: =IF(E75=0,0,(E75/AD75)-1) -> -0.37853403 | AI75: =IF(F75=0,0,(F75/AE75)-1) -> -0.37890295 | AJ75: =IF(G75=0,0,(G75/AF75)-1) -> -0.37859725
A76: 7.10 | B76: Chapim de chapa de aço galvanizado nº 24 desenvolvimento 33 cm | C76: =V76 -> 13 | D76: =W76 -> m | E76: =ROUND((X76*(1-$M$5))*(1+BDI!$C$21),2) -> 43.55 | F76: =ROUND((Y76*(1-$N$5))*(1+BDI!$C$21),2) -> 10.45 | G76: =F76+E76 -> 54 | H76: =C76*E76 -> 566.15 | I76: =C76*F76 -> 135.85 | J76: =SUM(E76:F76)*C76 -> 702 | V76: 13 | W76: m | X76: 54.41 | Y76: 13.06 | Z76: =SUM(X76:Y76) -> 67.47 | AB76: 13 | AC76: m | AD76: 70.09 | AE76: 16.82 | AF76: =SUM(AD76:AE76) -> 86.91 | AH76: =IF(E76=0,0,(E76/AD76)-1) -> -0.37865601 | AI76: =IF(F76=0,0,(F76/AE76)-1) -> -0.37871581 | AJ76: =IF(G76=0,0,(G76/AF76)-1) -> -0.37866759
A77: 7.11 | B77: Cobertura com telha de fibrocimento estrutural, com recobrimento longitudinal | C77: =V77 -> 113 | D77: =W77 -> m² | E77: =ROUND((X77*(1-$M$5))*(1+BDI!$C$21),2) -> 73.88 | F77: =ROUND((Y77*(1-$N$5))*(1+BDI!$C$21),2) -> 27.56 | G77: =F77+E77 -> 101.44 | H77: =C77*E77 -> 8348.44 | I77: =C77*F77 -> 3114.28 | J77: =SUM(E77:F77)*C77 -> 11462.72 | V77: 113 | W77: m² | X77: 92.29 | Y77: 34.43 | Z77: =SUM(X77:Y77) -> 126.72 | AB77: 113 | AC77: m² | AD77: 118.89 | AE77: 44.35 | AF77: =SUM(AD77:AE77) -> 163.24 | AH77: =IF(E77=0,0,(E77/AD77)-1) -> -0.37858525 | AI77: =IF(F77=0,0,(F77/AE77)-1) -> -0.37857948 | AJ77: =IF(G77=0,0,(G77/AF77)-1) -> -0.37858368
A78: 7.12 | B78: Estrutura de madeira para telha cerâmica, fibrocimento ou de concreto | C78: =V78 -> 50 | D78: =W78 -> m² | E78: =ROUND((X78*(1-$M$5))*(1+BDI!$C$21),2) -> 64.1 | F78: =ROUND((Y78*(1-$N$5))*(1+BDI!$C$21),2) -> 107.49 | G78: =F78+E78 -> 171.59 | H78: =C78*E78 -> 3205 | I78: =C78*F78 -> 5374.5 | J78: =SUM(E78:F78)*C78 -> 8579.5 | V78: 50 | W78: m² | X78: 80.08 | Y78: 134.28 | Z78: =SUM(X78:Y78) -> 214.36 | AB78: 50 | AC78: m² | AD78: 103.16 | AE78: 172.98 | AF78: =SUM(AD78:AE78) -> 276.14 | AH78: =IF(E78=0,0,(E78/AD78)-1) -> -0.37863513 | AI78: =IF(F78=0,0,(F78/AE78)-1) -> -0.37859868 | AJ78: =IF(G78=0,0,(G78/AF78)-1) -> -0.3786123
... A81: 7.15 | B81: Reparo emergencial de telhado e calhas | C81: =V81 -> 1 | D81: =W81 -> un | E81: =ROUND((X81*(1-$M$5))*(1+BDI!$C$21),2) -> 9.45 | F81: =ROUND((Y81*(1-$N$5))*(1+BDI!$C$21),2) -> 6.82 | G81: =F81+E81 -> 16.27 | H81: =C81*E81 -> 9.45 | I81: =C81*F81 -> 6.82 | J81: =SUM(E81:F81)*C81 -> 16.27 | V81: 1 | W81: un | X81: 11.81 | Y81: 8.52 | Z81: =SUM(X81:Y81) -> 20.33 | AB81: 1 | AC81: un | AD81: 15.21 | AE81: 10.98 | AF81: =SUM(AD81:AE81) -> 26.19 | AH81: =IF(E81=0,0,(E81/AD81)-1) -> -0.37869822 | AI81: =IF(F81=0,0,(F81/AE81)-1) -> -0.37887067 | AJ81: =IF(G81=0,0,(G81/AF81)-1) -> -0.37877052
A82: 8 | B82: IMPERMEABILIZAÇÃO | H82: =SUM(H83:H89) -> 76935.23 | I82: =SUM(I83:I89) -> 42489.42 | J82: =SUM(J83:J89) -> 119424.65 | AH82: =IF(E82=0,0,(E82/AD82)-1) -> 0 | AI82: =IF(F82=0,0,(F82/AE82)-1) -> 0 | AJ82: =IF(G82=0,0,(G82/AF82)-1) -> 0
A83: 8.1 | B83: Proteção mecânica de superfície com argamassa de cimento e areia | C83: =V83 -> 137 | D83: =W83 -> m² | E83: =ROUND((X83*(1-$M$5))*(1+BDI!$C$21),2) -> 17.78 | F83: =ROUND((Y83*(1-$N$5))*(1+BDI!$C$21),2) -> 18.74 | G83: =F83+E83 -> 36.52 | H83: =C83*E83 -> 2435.86 | I83: =C83*F83 -> 2567.38 | J83: =SUM(E83:F83)*C83 -> 5003.24 | V83: 137 | W83: m² | X83: 22.21 | Y83: 23.41 | Z83: =SUM(X83:Y83) -> 45.62 | AB83: 137 | AC83: m² | AD83: 28.61 | AE83: 30.16 | AF83: =SUM(AD83:AE83) -> 58.77 | AH83: =IF(E83=0,0,(E83/AD83)-1) -> -0.37853897 | AI83: =IF(F83=0,0,(F83/AE83)-1) -> -0.37864721 | AJ83: =IF(G83=0,0,(G83/AF83)-1) -> -0.37859452
A84: 8.2 | B84: Impermeabilização com manta asfáltica modificada com polímeros aluminizada | C84: =V84 -> 414 | D84: =W84 -> m² | E84: =ROUND((X84*(1-$M$5))*(1+BDI!$C$21),2) -> 64.79 | F84: =ROUND((Y84*(1-$N$5))*(1+BDI!$C$21),2) -> 18.25 | G84: =F84+E84 -> 83.04 | H84: =C84*E84 -> 26823.06 | I84: =C84*F84 -> 7555.5 | J84: =SUM(E84:F84)*C84 -> 34378.56 | V84: 414 | W84: m² | X84: 80.94 | Y84: 22.8 | Z84: =SUM(X84:Y84) -> 103.74 | AB84: 414 | AC84: m² | AD84: 104.27 | AE84: 29.37 | AF84: =SUM(AD84:AE84) -> 133.64 | AH84: =IF(E84=0,0,(E84/AD84)-1) -> -0.3786324 | AI84: =IF(F84=0,0,(F84/AE84)-1) -> -0.37861764 | AJ84: =IF(G84=0,0,(G84/AF84)-1) -> -0.37862915
A85: 8.3 | B85: Impermeabilização utilizando manta asfáltica polimérica (cobertura, lajes, banheiros, jardins, Reservatórios e similares) | C85: =V85 -> 262 | D85: =W85 -> m² | E85: =ROUND((X85*(1-$M$5))*(1+BDI!$C$21),2) -> 73.52 | F85: =ROUND((Y85*(1-$N$5))*(1+BDI!$C$21),2) -> 27.14 | G85: =F85+E85 -> 100.66 | H85: =C85*E85 -> 19262.24 | I85: =C85*F85 -> 7110.68 | J85: =SUM(E85:F85)*C85 -> 26372.92 | V85: 262 | W85: m² | X85: 91.84 | Y85: 33.9 | Z85: =SUM(X85:Y85) -> 125.74 | AB85: 262 | AC85: m² | AD85: 118.31 | AE85: 43.67 | AF85: =SUM(AD85:AE85) -> 161.98 | AH85: =IF(E85=0,0,(E85/AD85)-1) -> -0.37858169 | AI85: =IF(F85=0,0,(F85/AE85)-1) -> -0.37852072 | AJ85: =IF(G85=0,0,(G85/AF85)-1) -> -0.37856525
A86: 8.4 | B86: Impermeabilização de calha ou lajes descobertas com emulsão asfáltica com elastômeros, 3 demãos, com tela de poliéster | C86: =V86 -> 210 | D86: =W86 -> m² | E86: =ROUND((X86*(1-$M$5))*(1+BDI!$C$21),2) -> 42 | F86: =ROUND((Y86*(1-$N$5))*(1+BDI!$C$21),2) -> 17.99 | G86: =F86+E86 -> 59.99 | H86: =C86*E86 -> 8820 | I86: =C86*F86 -> 3777.9 | J86: =SUM(E86:F86)*C86 -> 12597.9 | V86: 210 | W86: m² | X86: 52.47 | Y86: 22.48 | Z86: =SUM(X86:Y86) -> 74.95 | AB86: 210 | AC86: m² | AD86: 67.59 | AE86: 28.96 | AF86: =SUM(AD86:AE86) -> 96.55 | AH86: =IF(E86=0,0,(E86/AD86)-1) -> -0.3786063 | AI86: =IF(F86=0,0,(F86/AE86)-1) -> -0.37879834 | AJ86: =IF(G86=0,0,(G86/AF86)-1) -> -0.3786639
A87: 8.5 | B87: Impermeabilização de superfície com impermeabilizante flexível à base acrílica | C87: =V87 -> 424 | D87: =W87 -> m² | E87: =ROUND((X87*(1-$M$5))*(1+BDI!$C$21),2) -> 44.82 | F87: =ROUND((Y87*(1-$N$5))*(1+BDI!$C$21),2) -> 48.64 | G87: =F87+E87 -> 93.46 | H87: =C87*E87 -> 19003.68 | I87: =C87*F87 -> 20623.36 | J87: =SUM(E87:F87)*C87 -> 39627.04 | V87: 424 | W87: m² | X87: 55.99 | Y87: 60.76 | Z87: =SUM(X87:Y87) -> 116.75 | AB87: 424 | AC87: m² | AD87: 72.13 | AE87: 78.27 | AF87: =SUM(AD87:AE87) -> 150.4 | AH87: =IF(E87=0,0,(E87/AD87)-1) -> -0.37862193 | AI87: =IF(F87=0,0,(F87/AE87)-1) -> -0.37856139 | AJ87: =IF(G87=0,0,(G87/AF87)-1) -> -0.37859043
A88: 8.6 | B88: Impermeabilização com argamassa polimérica impermeabilizante | C88: =V88 -> 60 | D88: =W88 -> m² | E88: =ROUND((X88*(1-$M$5))*(1+BDI!$C$21),2) -> 7.9 | F88: =ROUND((Y88*(1-$N$5))*(1+BDI!$C$21),2) -> 13.9 | G88: =F88+E88 -> 21.8 | H88: =C88*E88 -> 474 | I88: =C88*F88 -> 834 | J88: =SUM(E88:F88)*C88 -> 1308 | V88: 60 | W88: m² | X88: 9.87 | Y88: 17.36 | Z88: =SUM(X88:Y88) -> 27.23 | AB88: 60 | AC88: m² | AD88: 12.71 | AE88: 22.36 | AF88: =SUM(AD88:AE88) -> 35.07 | AH88: =IF(E88=0,0,(E88/AD88)-1) -> -0.37844217 | AI88: =IF(F88=0,0,(F88/AE88)-1) -> -0.3783542 | AJ88: =IF(G88=0,0,(G88/AF88)-1) -> -0.37838608
A89: 8.7 | B89: Impermeabilização com membrana de poliuretano (PU) | C89: =V89 -> 1 | D89: =W89 -> m² | E89: =ROUND((X89*(1-$M$5))*(1+BDI!$C$21),2) -> 116.39 | F89: =ROUND((Y89*(1-$N$5))*(1+BDI!$C$21),2) -> 20.6 | G89: =F89+E89 -> 136.99 | H89: =C89*E89 -> 116.39 | I89: =C89*F89 -> 20.6 | J89: =SUM(E89:F89)*C89 -> 136.99 | V89: 1 | W89: m² | X89: 145.4 | Y89: 25.74 | Z89: =SUM(X89:Y89) -> 171.14 | AB89: 1 | AC89: m² | AD89: 187.3 | AE89: 33.16 | AF89: =SUM(AD89:AE89) -> 220.46 | AH89: =IF(E89=0,0,(E89/AD89)-1) -> -0.3785905 | AI89: =IF(F89=0,0,(F89/AE89)-1) -> -0.3787696 | AJ89: =IF(G89=0,0,(G89/AF89)-1) -> -0.37861744
A90: 9 | B90: TRATAMENTO TÉRMICO E ACÚSTICO | H90: 0 | I90: 0 | J90: 0 | AH90: =IF(E90=0,0,(E90/AD90)-1) -> 0 | AI90: =IF(F90=0,0,(F90/AE90)-1) -> 0 | AJ90: =IF(G90=0,0,(G90/AF90)-1) -> 0
A91: 10 | B91: PAVIMENTAÇÃO | H91: =SUM(H92:H115) -> 410711.46 | I91: =SUM(I92:I115) -> 29774.29 | J91: =SUM(J92:J115) -> 440485.75 | AH91: =IF(E91=0,0,(E91/AD91)-1) -> 0 | AI91: =IF(F91=0,0,(F91/AE91)-1) -> 0 | AJ91: =IF(G91=0,0,(G91/AF91)-1) -> 0
A92: 10.1 | B92: Regularização de base ou contrapiso | C92: =V92 -> 416 | D92: =W92 -> m² | E92: =ROUND((X92*(1-$M$5))*(1+BDI!$C$21),2) -> 10.75 | F92: =ROUND((Y92*(1-$N$5))*(1+BDI!$C$21),2) -> 11.33 | G92: =F92+E92 -> 22.08 | H92: =C92*E92 -> 4472 | I92: =C92*F92 -> 4713.28 | J92: =SUM(E92:F92)*C92 -> 9185.28 | V92: 416 | W92: m² | X92: 13.43 | Y92: 14.15 | Z92: =SUM(X92:Y92) -> 27.58 | AB92: 416 | AC92: m² | AD92: 17.3 | AE92: 18.23 | AF92: =SUM(AD92:AE92) -> 35.53 | AH92: =IF(E92=0,0,(E92/AD92)-1) -> -0.37861272 | AI92: =IF(F92=0,0,(F92/AE92)-1) -> -0.37849698 | AJ92: =IF(G92=0,0,(G92/AF92)-1) -> -0.37855334
A93: 10.2 | B93: Regularização de piso para piso vinílico ou tátil em borracha | C93: =V93 -> 336 | D93: =W93 -> m² | E93: =ROUND((X93*(1-$M$5))*(1+BDI!$C$21),2) -> 14.51 | F93: =ROUND((Y93*(1-$N$5))*(1+BDI!$C$21),2) -> 18.12 | G93: =F93+E93 -> 32.63 | H93: =C93*E93 -> 4875.36 | I93: =C93*F93 -> 6088.32 | J93: =SUM(E93:F93)*C93 -> 10963.68 | V93: 336 | W93: m² | X93: 18.13 | Y93: 22.64 | Z93: =SUM(X93:Y93) -> 40.77 | AB93: 336 | AC93: m² | AD93: 23.36 | AE93: 29.16 | AF93: =SUM(AD93:AE93) -> 52.52 | AH93: =IF(E93=0,0,(E93/AD93)-1) -> -0.37885274 | AI93: =IF(F93=0,0,(F93/AE93)-1) -> -0.37860082 | AJ93: =IF(G93=0,0,(G93/AF93)-1) -> -0.37871287
A94: 10.3 | B94: Granito para revestimento (piso ou parede) Cinza Andorinha, assente com argamassa | C94: =V94 -> 17 | D94: =W94 -> m² | E94: =ROUND((X94*(1-$M$5))*(1+BDI!$C$21),2) -> 361.48 | F94: =ROUND((Y94*(1-$N$5))*(1+BDI!$C$21),2) -> 41.87 | G94: =F94+E94 -> 403.35 | H94: =C94*E94 -> 6145.16 | I94: =C94*F94 -> 711.79 | J94: =SUM(E94:F94)*C94 -> 6856.95 | V94: 17 | W94: m² | X94: 451.57 | Y94: 52.3 | Z94: =SUM(X94:Y94) -> 503.87 | AB94: 17 | AC94: m² | AD94: 581.71 | AE94: 67.37 | AF94: =SUM(AD94:AE94) -> 649.08 | AH94: =IF(E94=0,0,(E94/AD94)-1) -> -0.37859071 | AI94: =IF(F94=0,0,(F94/AE94)-1) -> -0.37850675 | AJ94: =IF(G94=0,0,(G94/AF94)-1) -> -0.37858199
A95: 10.4 | B95: Rodapé em granito Cinza Andorinha, assentado e rejuntado | C95: =V95 -> 26 | D95: =W95 -> m | E95: =ROUND((X95*(1-$M$5))*(1+BDI!$C$21),2) -> 59.76 | F95: =ROUND((Y95*(1-$N$5))*(1+BDI!$C$21),2) -> 10.55 | G95: =F95+E95 -> 70.31 | H95: =C95*E95 -> 1553.76 | I95: =C95*F95 -> 274.3 | J95: =SUM(E95:F95)*C95 -> 1828.06 | V95: 26 | W95: m | X95: 74.66 | Y95: 13.18 | Z95: =SUM(X95:Y95) -> 87.84 | AB95: 26 | AC95: m | AD95: 96.18 | AE95: 16.98 | AF95: =SUM(AD95:AE95) -> 113.16 | AH95: =IF(E95=0,0,(E95/AD95)-1) -> -0.378665 | AI95: =IF(F95=0,0,(F95/AE95)-1) -> -0.3786808 | AJ95: =IF(G95=0,0,(G95/AF95)-1) -> -0.37866737
A96: 10.5 | B96: Peitoril ou soleira de granito, assentado e rejuntado | C96: =V96 -> 7 | D96: =W96 -> m | E96: =ROUND((X96*(1-$M$5))*(1+BDI!$C$21),2) -> 81.34 | F96: =ROUND((Y96*(1-$N$5))*(1+BDI!$C$21),2) -> 19.27 | G96: =F96+E96 -> 100.61 | H96: =C96*E96 -> 569.38 | I96: =C96*F96 -> 134.89 | J96: =SUM(E96:F96)*C96 -> 704.27 | V96: 7 | W96: m | X96: 101.61 | Y96: 24.07 | Z96: =SUM(X96:Y96) -> 125.68 | AB96: 7 | AC96: m | AD96: 130.89 | AE96: 31.01 | AF96: =SUM(AD96:AE96) -> 161.9 | AH96: =IF(E96=0,0,(E96/AD96)-1) -> -0.37856215 | AI96: =IF(F96=0,0,(F96/AE96)-1) -> -0.37858755 | AJ96: =IF(G96=0,0,(G96/AF96)-1) -> -0.37856702
A97: 10.6 | B97: Granito branco para revestimento (piso ou parede), assente com argamassa | C97: =V97 -> 1 | D97: =W97 -> m² | E97: =ROUND((X97*(1-$M$5))*(1+BDI!$C$21),2) -> 669.24 | F97: =ROUND((Y97*(1-$N$5))*(1+BDI!$C$21),2) -> 41.87 | G97: =F97+E97 -> 711.11 | H97: =C97*E97 -> 669.24 | I97: =C97*F97 -> 41.87 | J97: =SUM(E97:F97)*C97 -> 711.11 | V97: 1 | W97: m² | X97: 836.04 | Y97: 52.3 | Z97: =SUM(X97:Y97) -> 888.34 | AB97: 1 | AC97: m² | AD97: 1076.99 | AE97: 67.37 | AF97: =SUM(AD97:AE97) -> 1144.36 | AH97: =IF(E97=0,0,(E97/AD97)-1) -> -0.37860147 | AI97: =IF(F97=0,0,(F97/AE97)-1) -> -0.37850675 | AJ97: =IF(G97=0,0,(G97/AF97)-1) -> -0.3785959
A98: 10.7 | B98: Rodapé em granito branco, assentado e rejuntado | C98: =V98 -> 1 | D98: =W98 -> m | E98: =ROUND((X98*(1-$M$5))*(1+BDI!$C$21),2) -> 63.95 | F98: =ROUND((Y98*(1-$N$5))*(1+BDI!$C$21),2) -> 10.55 | G98: =F98+E98 -> 74.5 | H98: =C98*E98 -> 63.95 | I98: =C98*F98 -> 10.55 | J98: =SUM(E98:F98)*C98 -> 74.5 | V98: 1 | W98: m | X98: 79.89 | Y98: 13.18 | Z98: =SUM(X98:Y98) -> 93.07 | AB98: 1 | AC98: m | AD98: 102.91 | AE98: 16.98 | AF98: =SUM(AD98:AE98) -> 119.89 | AH98: =IF(E98=0,0,(E98/AD98)-1) -> -0.37858323 | AI98: =IF(F98=0,0,(F98/AE98)-1) -> -0.3786808 | AJ98: =IF(G98=0,0,(G98/AF98)-1) -> -0.37859705
A99: 10.8 | B99: Bloco de concreto intertravado | C99: =V99 -> 12 | D99: =W99 -> m² | E99: =ROUND((X99*(1-$M$5))*(1+BDI!$C$21),2) -> 54.75 | F99: =ROUND((Y99*(1-$N$5))*(1+BDI!$C$21),2) -> 7.2 | G99: =F99+E99 -> 61.95 | H99: =C99*E99 -> 657 | I99: =C99*F99 -> 86.4 | J99: =SUM(E99:F99)*C99 -> 743.4 | V99: 12 | W99: m² | X99: 68.4 | Y99: 8.99 | Z99: =SUM(X99:Y99) -> 77.39 | AB99: 12 | AC99: m² | AD99: 88.11 | AE99: 11.58 | AF99: =SUM(AD99:AE99) -> 99.69 | AH99: =IF(E99=0,0,(E99/AD99)-1) -> -0.37861764 | AI99: =IF(F99=0,0,(F99/AE99)-1) -> -0.37823834 | AJ99: =IF(G99=0,0,(G99/AF99)-1) -> -0.37857358
A100: 10.9 | B100: Piso em pedra portuguesa, basalto, calcário ou granito sem polimento. | C100: =V100 -> 42 | D100: =W100 -> m² | E100: =ROUND((X100*(1-$M$5))*(1+BDI!$C$21),2) -> 142.01 | F100: =ROUND((Y100*(1-$N$5))*(1+BDI!$C$21),2) -> 45.12 | G100: =F100+E100 -> 187.13 | H100: =C100*E100 -> 5964.42 | I100: =C100*F100 -> 1895.04 | J100: =SUM(E100:F100)*C100 -> 7859.46 | V100: 42 | W100: m² | X100: 177.4 | Y100: 56.36 | Z100: =SUM(X100:Y100) -> 233.76 | AB100: 42 | AC100: m² | AD100: 228.53 | AE100: 72.6 | AF100: =SUM(AD100:AE100) -> 301.13 | AH100: =IF(E100=0,0,(E100/AD100)-1) -> -0.37859362 | AI100: =IF(F100=0,0,(F100/AE100)-1) -> -0.3785124 | AJ100: =IF(G100=0,0,(G100/AF100)-1) -> -0.37857404
A101: 10.10 | B101: Piso mármore branco, assentado e rejuntado | C101: =V101 -> 1 | D101: =W101 -> m² | E101: =ROUND((X101*(1-$M$5))*(1+BDI!$C$21),2) -> 453.28 | F101: =ROUND((Y101*(1-$N$5))*(1+BDI!$C$21),2) -> 41.87 | G101: =F101+E101 -> 495.15 | H101: =C101*E101 -> 453.28 | I101: =C101*F101 -> 41.87 | J101: =SUM(E101:F101)*C101 -> 495.15 | V101: 1 | W101: m² | X101: 566.25 | Y101: 52.3 | Z101: =SUM(X101:Y101) -> 618.55 | AB101: 1 | AC101: m² | AD101: 729.44 | AE101: 67.37 | AF101: =SUM(AD101:AE101) -> 796.81 | AH101: =IF(E101=0,0,(E101/AD101)-1) -> -0.3785918 | AI101: =IF(F101=0,0,(F101/AE101)-1) -> -0.37850675 | AJ101: =IF(G101=0,0,(G101/AF101)-1) -> -0.37858461
A102: 10.11 | B102: Piso em ladrilho hidráulico, assentado com argamassa | C102: =V102 -> 43 | D102: =W102 -> m² | E102: =ROUND((X102*(1-$M$5))*(1+BDI!$C$21),2) -> 82.95 | F102: =ROUND((Y102*(1-$N$5))*(1+BDI!$C$21),2) -> 76.14 | G102: =F102+E102 -> 159.09 | H102: =C102*E102 -> 3566.85 | I102: =C102*F102 -> 3274.02 | J102: =SUM(E102:F102)*C102 -> 6840.87 | V102: 43 | W102: m² | X102: 103.63 | Y102: 95.12 | Z102: =SUM(X102:Y102) -> 198.75 | AB102: 43 | AC102: m² | AD102: 133.5 | AE102: 122.53 | AF102: =SUM(AD102:AE102) -> 256.03 | AH102: =IF(E102=0,0,(E102/AD102)-1) -> -0.37865169 | AI102: =IF(F102=0,0,(F102/AE102)-1) -> -0.37860116 | AJ102: =IF(G102=0,0,(G102/AF102)-1) -> -0.3786275
A103: 10.12 | B103: Piso cimentado com argamassa e com junta plástica para dilatação. | C103: =V103 -> 41 | D103: =W103 -> m² | E103: =ROUND((X103*(1-$M$5))*(1+BDI!$C$21),2) -> 23.8 | F103: =ROUND((Y103*(1-$N$5))*(1+BDI!$C$21),2) -> 13.53 | G103: =F103+E103 -> 37.33 | H103: =C103*E103 -> 975.8 | I103: =C103*F103 -> 554.73 | J103: =SUM(E103:F103)*C103 -> 1530.53 | V103: 41 | W103: m² | X103: 29.73 | Y103: 16.9 | Z103: =SUM(X103:Y103) -> 46.63 | AB103: 41 | AC103: m² | AD103: 38.3 | AE103: 21.77 | AF103: =SUM(AD103:AE103) -> 60.07 | AH103: =IF(E103=0,0,(E103/AD103)-1) -> -0.37859008 | AI103: =IF(F103=0,0,(F103/AE103)-1) -> -0.37850253 | AJ103: =IF(G103=0,0,(G103/AF103)-1) -> -0.37855835
... A115: 10.24 | B115: Aplicação de Solução Antiderrapante em Pisos Frios, Inclusive mão de obra especializada | C115: =V115 -> 2 | D115: =W115 -> m² | E115: =ROUND((X115*(1-$M$5))*(1+BDI!$C$21),2) -> 39.88 | F115: =ROUND((Y115*(1-$N$5))*(1+BDI!$C$21),2) -> 0 | G115: =F115+E115 -> 39.88 | H115: =C115*E115 -> 79.76 | I115: =C115*F115 -> 0 | J115: =SUM(E115:F115)*C115 -> 79.76 | V115: 2 | W115: m² | X115: 49.82 | Y115: 0 | Z115: =SUM(X115:Y115) -> 49.82 | AB115: 2 | AC115: m² | AD115: 64.18 | AE115: 0 | AF115: =SUM(AD115:AE115) -> 64.18 | AH115: =IF(E115=0,0,(E115/AD115)-1) -> -0.37862262 | AI115: =IF(F115=0,0,(F115/AE115)-1) -> 0 | AJ115: =IF(G115=0,0,(G115/AF115)-1) -> -0.37862262
A116: 11 | B116: REVESTIMENTOS | H116: =SUM(H117:H125) -> 22411.85 | I116: =SUM(I117:I125) -> 11452.03 | J116: =SUM(J117:J125) -> 33863.88 | AH116: =IF(E116=0,0,(E116/AD116)-1) -> 0 | AI116: =IF(F116=0,0,(F116/AE116)-1) -> 0 | AJ116: =IF(G116=0,0,(G116/AF116)-1) -> 0
A117: 11.1 | B117: Painéis de alumínio - ACM | C117: =V117 -> 1 | D117: =W117 -> m² | E117: =ROUND((X117*(1-$M$5))*(1+BDI!$C$21),2) -> 118.25 | F117: =ROUND((Y117*(1-$N$5))*(1+BDI!$C$21),2) -> 52.81 | G117: =F117+E117 -> 171.06 | H117: =C117*E117 -> 118.25 | I117: =C117*F117 -> 52.81 | J117: =SUM(E117:F117)*C117 -> 171.06 | V117: 1 | W117: m² | X117: 147.72 | Y117: 65.97 | Z117: =SUM(X117:Y117) -> 213.69 | AB117: 1 | AC117: m² | AD117: 190.29 | AE117: 84.98 | AF117: =SUM(AD117:AE117) -> 275.27 | AH117: =IF(E117=0,0,(E117/AD117)-1) -> -0.37858006 | AI117: =IF(F117=0,0,(F117/AE117)-1) -> -0.37855966 | AJ117: =IF(G117=0,0,(G117/AF117)-1) -> -0.37857376
A118: 11.2 | B118: Chapisco para parede interna ou externa com argamassa de cimento e areia. | C118: =V118 -> 179 | D118: =W118 -> m² | E118: =ROUND((X118*(1-$M$5))*(1+BDI!$C$21),2) -> 1.79 | F118: =ROUND((Y118*(1-$N$5))*(1+BDI!$C$21),2) -> 4.53 | G118: =F118+E118 -> 6.32 | H118: =C118*E118 -> 320.41 | I118: =C118*F118 -> 810.87 | J118: =SUM(E118:F118)*C118 -> 1131.28 | V118: 179 | W118: m² | X118: 2.24 | Y118: 5.66 | Z118: =SUM(X118:Y118) -> 7.9 | AB118: 179 | AC118: m² | AD118: 2.89 | AE118: 7.29 | AF118: =SUM(AD118:AE118) -> 10.18 | AH118: =IF(E118=0,0,(E118/AD118)-1) -> -0.38062284 | AI118: =IF(F118=0,0,(F118/AE118)-1) -> -0.37860082 | AJ118: =IF(G118=0,0,(G118/AF118)-1) -> -0.37917485
A119: 11.3 | B119: Emboço ou reboco para parede interna ou externa ou teto. | C119: =V119 -> 321 | D119: =W119 -> m² | E119: =ROUND((X119*(1-$M$5))*(1+BDI!$C$21),2) -> 14.51 | F119: =ROUND((Y119*(1-$N$5))*(1+BDI!$C$21),2) -> 20.96 | G119: =F119+E119 -> 35.47 | H119: =C119*E119 -> 4657.71 | I119: =C119*F119 -> 6728.16 | J119: =SUM(E119:F119)*C119 -> 11385.87 | V119: 321 | W119: m² | X119: 18.13 | Y119: 26.19 | Z119: =SUM(X119:Y119) -> 44.32 | AB119: 321 | AC119: m² | AD119: 23.36 | AE119: 33.74 | AF119: =SUM(AD119:AE119) -> 57.1 | AH119: =IF(E119=0,0,(E119/AD119)-1) -> -0.37885274 | AI119: =IF(F119=0,0,(F119/AE119)-1) -> -0.3787789 | AJ119: =IF(G119=0,0,(G119/AF119)-1) -> -0.37880911
A120: 11.4 | B120: Revestimento cerâmico assentado com argamassa pré-fabricada e rejuntado | C120: =V120 -> 46 | D120: =W120 -> m² | E120: =ROUND((X120*(1-$M$5))*(1+BDI!$C$21),2) -> 28.72 | F120: =ROUND((Y120*(1-$N$5))*(1+BDI!$C$21),2) -> 33.48 | G120: =F120+E120 -> 62.2 | H120: =C120*E120 -> 1321.12 | I120: =C120*F120 -> 1540.08 | J120: =SUM(E120:F120)*C120 -> 2861.2 | V120: 46 | W120: m² | X120: 35.88 | Y120: 41.82 | Z120: =SUM(X120:Y120) -> 77.7 | AB120: 46 | AC120: m² | AD120: 46.22 | AE120: 53.87 | AF120: =SUM(AD120:AE120) -> 100.09 | AH120: =IF(E120=0,0,(E120/AD120)-1) -> -0.37862397 | AI120: =IF(F120=0,0,(F120/AE120)-1) -> -0.37850381 | AJ120: =IF(G120=0,0,(G120/AF120)-1) -> -0.3785593
A121: 11.5 | B121: Revestimento (parede) em Pastilha de vidro, assentada com argamassa colante e rejunte. | C121: =V121 -> 57 | D121: =W121 -> m² | E121: =ROUND((X121*(1-$M$5))*(1+BDI!$C$21),2) -> 234.28 | F121: =ROUND((Y121*(1-$N$5))*(1+BDI!$C$21),2) -> 35.56 | G121: =F121+E121 -> 269.84 | H121: =C121*E121 -> 13353.96 | I121: =C121*F121 -> 2026.92 | J121: =SUM(E121:F121)*C121 -> 15380.88 | V121: 57 | W121: m² | X121: 292.67 | Y121: 44.42 | Z121: =SUM(X121:Y121) -> 337.09 | AB121: 57 | AC121: m² | AD121: 377.02 | AE121: 57.22 | AF121: =SUM(AD121:AE121) -> 434.24 | AH121: =IF(E121=0,0,(E121/AD121)-1) -> -0.3786006 | AI121: =IF(F121=0,0,(F121/AE121)-1) -> -0.37853897 | AJ121: =IF(G121=0,0,(G121/AF121)-1) -> -0.37859248
A122: 11.6 | B122: Laminado melamínico para revestimento (piso ou parede) interno | C122: =V122 -> 15 | D122: =W122 -> m² | E122: =ROUND((X122*(1-$M$5))*(1+BDI!$C$21),2) -> 82.33 | F122: =ROUND((Y122*(1-$N$5))*(1+BDI!$C$21),2) -> 8.27 | G122: =F122+E122 -> 90.6 | H122: =C122*E122 -> 1234.95 | I122: =C122*F122 -> 124.05 | J122: =SUM(E122:F122)*C122 -> 1359 | V122: 15 | W122: m² | X122: 102.85 | Y122: 10.33 | Z122: =SUM(X122:Y122) -> 113.18 | AB122: 15 | AC122: m² | AD122: 132.49 | AE122: 13.31 | AF122: =SUM(AD122:AE122) -> 145.8 | AH122: =IF(E122=0,0,(E122/AD122)-1) -> -0.37859461 | AI122: =IF(F122=0,0,(F122/AE122)-1) -> -0.37866266 | AJ122: =IF(G122=0,0,(G122/AF122)-1) -> -0.37860082
A123: 11.7 | B123: Revestimento de parede com pedra São Tomé filetada (tipo "canjiquinha") | C123: =V123 -> 3 | D123: =W123 -> m² | E123: =ROUND((X123*(1-$M$5))*(1+BDI!$C$21),2) -> 245.4 | F123: =ROUND((Y123*(1-$N$5))*(1+BDI!$C$21),2) -> 30.57 | G123: =F123+E123 -> 275.97 | H123: =C123*E123 -> 736.2 | I123: =C123*F123 -> 91.71 | J123: =SUM(E123:F123)*C123 -> 827.91 | V123: 3 | W123: m² | X123: 306.56 | Y123: 38.19 | Z123: =SUM(X123:Y123) -> 344.75 | AB123: 3 | AC123: m² | AD123: 394.91 | AE123: 49.2 | AF123: =SUM(AD123:AE123) -> 444.11 | AH123: =IF(E123=0,0,(E123/AD123)-1) -> -0.37859259 | AI123: =IF(F123=0,0,(F123/AE123)-1) -> -0.37865854 | AJ123: =IF(G123=0,0,(G123/AF123)-1) -> -0.3785999
A124: 11.8 | B124: Revestimento em mármore branco (parede), assentado e rejuntado | C124: =V124 -> 1 | D124: =W124 -> m² | E124: =ROUND((X124*(1-$M$5))*(1+BDI!$C$21),2) -> 453.28 | F124: =ROUND((Y124*(1-$N$5))*(1+BDI!$C$21),2) -> 41.87 | G124: =F124+E124 -> 495.15 | H124: =C124*E124 -> 453.28 | I124: =C124*F124 -> 41.87 | J124: =SUM(E124:F124)*C124 -> 495.15 | V124: 1 | W124: m² | X124: 566.25 | Y124: 52.3 | Z124: =SUM(X124:Y124) -> 618.55 | AB124: 1 | AC124: m² | AD124: 729.44 | AE124: 67.37 | AF124: =SUM(AD124:AE124) -> 796.81 | AH124: =IF(E124=0,0,(E124/AD124)-1) -> -0.3785918 | AI124: =IF(F124=0,0,(F124/AE124)-1) -> -0.37850675 | AJ124: =IF(G124=0,0,(G124/AF124)-1) -> -0.37858461
A125: 11.9 | B125: Revestimento em Pastilha Cerâmica, assentada com argamassa colante e rejunte. | C125: =V125 -> 1 | D125: =W125 -> m² | E125: =ROUND((X125*(1-$M$5))*(1+BDI!$C$21),2) -> 215.97 | F125: =ROUND((Y125*(1-$N$5))*(1+BDI!$C$21),2) -> 35.56 | G125: =F125+E125 -> 251.53 | H125: =C125*E125 -> 215.97 | I125: =C125*F125 -> 35.56 | J125: =SUM(E125:F125)*C125 -> 251.53 | V125: 1 | W125: m² | X125: 269.8 | Y125: 44.42 | Z125: =SUM(X125:Y125) -> 314.22 | AB125: 1 | AC125: m² | AD125: 347.56 | AE125: 57.22 | AF125: =SUM(AD125:AE125) -> 404.78 | AH125: =IF(E125=0,0,(E125/AD125)-1) -> -0.37861089 | AI125: =IF(F125=0,0,(F125/AE125)-1) -> -0.37853897 | AJ125: =IF(G125=0,0,(G125/AF125)-1) -> -0.37860072
A126: 12 | B126: DIVISÓRIAS, FORROS E PISOS FALSOS | H126: =SUM(H127:H140) -> 122406.27 | I126: =SUM(I127:I140) -> 37201.31 | J126: =SUM(J127:J140) -> 159607.58 | AH126: =IF(E126=0,0,(E126/AD126)-1) -> 0 | AI126: =IF(F126=0,0,(F126/AE126)-1) -> 0 | AJ126: =IF(G126=0,0,(G126/AF126)-1) -> 0
A127: 12.1 | B127: Divisória texturizada cega | C127: =V127 -> 72 | D127: =W127 -> m² | E127: =ROUND((X127*(1-$M$5))*(1+BDI!$C$21),2) -> 156.26 | F127: =ROUND((Y127*(1-$N$5))*(1+BDI!$C$21),2) -> 37.28 | G127: =F127+E127 -> 193.54 | H127: =C127*E127 -> 11250.72 | I127: =C127*F127 -> 2684.16 | J127: =SUM(E127:F127)*C127 -> 13934.88 | V127: 72 | W127: m² | X127: 195.2 | Y127: 46.57 | Z127: =SUM(X127:Y127) -> 241.77 | AB127: 72 | AC127: m² | AD127: 251.46 | AE127: 59.99 | AF127: =SUM(AD127:AE127) -> 311.45 | AH127: =IF(E127=0,0,(E127/AD127)-1) -> -0.37858904 | AI127: =IF(F127=0,0,(F127/AE127)-1) -> -0.37856309 | AJ127: =IF(G127=0,0,(G127/AF127)-1) -> -0.37858404
A128: 12.2 | B128: Divisória texturizada cega/vidro | C128: =V128 -> 1 | D128: =W128 -> m² | E128: =ROUND((X128*(1-$M$5))*(1+BDI!$C$21),2) -> 151.74 | F128: =ROUND((Y128*(1-$N$5))*(1+BDI!$C$21),2) -> 54.04 | G128: =F128+E128 -> 205.78 | H128: =C128*E128 -> 151.74 | I128: =C128*F128 -> 54.04 | J128: =SUM(E128:F128)*C128 -> 205.78 | V128: 1 | W128: m² | X128: 189.56 | Y128: 67.51 | Z128: =SUM(X128:Y128) -> 257.07 | AB128: 1 | AC128: m² | AD128: 244.19 | AE128: 86.97 | AF128: =SUM(AD128:AE128) -> 331.16 | AH128: =IF(E128=0,0,(E128/AD128)-1) -> -0.37859863 | AI128: =IF(F128=0,0,(F128/AE128)-1) -> -0.37863631 | AJ128: =IF(G128=0,0,(G128/AF128)-1) -> -0.37860853
A129: 12.3 | B129: Porta de divisória, Inclui batente e guarnições. | C129: =V129 -> 11 | D129: =W129 -> un | E129: =ROUND((X129*(1-$M$5))*(1+BDI!$C$21),2) -> 420.28 | F129: =ROUND((Y129*(1-$N$5))*(1+BDI!$C$21),2) -> 37.28 | G129: =F129+E129 -> 457.56 | H129: =C129*E129 -> 4623.08 | I129: =C129*F129 -> 410.08 | J129: =SUM(E129:F129)*C129 -> 5033.16 | V129: 11 | W129: un | X129: 525.03 | Y129: 46.57 | Z129: =SUM(X129:Y129) -> 571.6 | AB129: 11 | AC129: un | AD129: 676.34 | AE129: 59.99 | AF129: =SUM(AD129:AE129) -> 736.33 | AH129: =IF(E129=0,0,(E129/AD129)-1) -> -0.37859656 | AI129: =IF(F129=0,0,(F129/AE129)-1) -> -0.37856309 | AJ129: =IF(G129=0,0,(G129/AF129)-1) -> -0.37859384
A130: 12.4 | B130: Forro de fibra mineral, incluindo fixação, com estrutura | C130: =V130 -> 517 | D130: =W130 -> m² | E130: =ROUND((X130*(1-$M$5))*(1+BDI!$C$21),2) -> 108.71 | F130: =ROUND((Y130*(1-$N$5))*(1+BDI!$C$21),2) -> 12.34 | G130: =F130+E130 -> 121.05 | H130: =C130*E130 -> 56203.07 | I130: =C130*F130 -> 6379.78 | J130: =SUM(E130:F130)*C130 -> 62582.85 | V130: 517 | W130: m² | X130: 135.8 | Y130: 15.41 | Z130: =SUM(X130:Y130) -> 151.21 | AB130: 517 | AC130: m² | AD130: 174.94 | AE130: 19.85 | AF130: =SUM(AD130:AE130) -> 194.79 | AH130: =IF(E130=0,0,(E130/AD130)-1) -> -0.37858694 | AI130: =IF(F130=0,0,(F130/AE130)-1) -> -0.37833753 | AJ130: =IF(G130=0,0,(G130/AF130)-1) -> -0.37856153
...

Sheet Prefixos
A1: Relação das Dependências do Lote 03 - São José dos Campos (SP)
A4: PREFIXO | B4: SB | C4: NOME DA AGÊNCIA | D4: ENDEREÇO | E4: MUNICÍPIO
A5: 76 | B5: 0 | C5: TAUBATE | D5: PCA.DOM EPAMINONDAS 84 | E5: TAUBATE
A6: 76 | B6: 4 | C6: MEX-1.B AV EX | D6: ESTR.DOS REMEDIOS 2135 | E6: TAUBATE
A7: 175 | B7: 0 | C7: SAO JOSE DOS CAMPOS | D7: AVENIDA DOUTOR NELSON D'AVILA _149 | E7: SAO JOSE DOS CAMPOS
A8: 294 | B8: 0 | C8: MOGI DAS CRUZES | D8: AV.VOL.FERNANDO PINHEIRO FRANCO 432 | E8: MOGI DAS CRUZES
A9: 306 | B9: 0 | C9: GUARATINGUETA | D9: RUA MONSENHOR FILIPPO 193 | E9: GUARATINGUETA
A10: 306 | B10: 1 | C10: FAB-E E A R | D10: AV.BRIG.ADHEMAR LIRIO S/N | E10: GUARATINGUETA
A11: 449 | B11: 0 | C11: CRUZEIRO-SP | D11: R.CAP.NECO 320/326 | E11: CRUZEIRO
A12: 574 | B12: 0 | C12: PINDAMONHANGABA | D12: PCA.MONS.MARCONDES 90 | E12: PINDAMONHANGABA
A13: 683 | B13: 0 | C13: JACAREI | D13: AV SEN JOAQUIM M M DE SIQUEIRA 25 | E13: JACAREI
A14: 715 | B14: 0 | C14: SAO SEBASTIAO-SP | D14: R.DUQUE DE CAXIAS 204 | E14: SAO SEBASTIAO
A15: 718 | B15: 0 | C15: SUZANO | D15: RUA GENERAL FRANCISCO GLICERIO 472 | E15: SUZANO
A16: 857 | B16: 0 | C16: LORENA | D16: PCA.DR.ARNOLFO DE AZEVEDO 93 | E16: LORENA
... A112: 175 | B112: 26 | C112: PETROBRAS-REF.H.LAG | D112: ROD.PRES.DUTRA KM 143 S/N | E112: SAO JOSE DOS CAMPOS

Sheet BDI
B1: O interessado deverá preencher os campos em amarelo de forma a obter o valor do BDI. | E1: O BDI pode ser alterado pela interessada. A alteração do BDI afeta o valor final da proposta. O valor do BDI deverá ser igual ao da proposta a ser apresentada.
B3: COMPOSIÇÃO ESTIMADA DO BDI (DESONERADO)
B6: ÍNDICES BDI - Serviços, subcontratações e acionamentos de Serviços de Engenharia.
B9: CUSTOS INDIRETOS
B10: Administração Central (AC) | C10: 0.03
B11: Seguros (S) + Garantia (G) | C11: 0.008
B12: Riscos R) | C12: 0.0097
B13: Despesas Financeiras (DF) | C13: 0.0059
B14: BONIFICAÇÃO
B15: Lucro Bruto (LB) | C15: 0.0616
B16: TRIBUTOS (T)
B17: ISS | C17: 0.05
B18: PIS / PASEP | C18: 0.0065
B19: COFINS | C19: 0.03
B20: CPRB | C20: 0.045
B21: BDI SERVIÇOS | C21: =ROUND(((1+(C10+C11+C12))*(1+C13)*(1+C15))/(1-(C17+C18+C19+C20))-1,4) -> 0.2882
B22: BDI = [[(1+(AC+S+G+R))*(1+DF)*(1+LB)]/(1-T)]-1
B26: 1 - O cálculo do BDI segue a metodologia estabelecida no item 9.10 do Voto do Acórdão 2369/2011 - TCU - Plenário. O IR e a CSLL não fazem parte do cálculo. 2 - Valores Referenciais dados pelo Acórdão 2622/2013 - TCU - Plenário. 3 - A parcela referente aos Seguros (S) é inversa à parcela de Riscos (R), ou seja, quanto maior a cobertura dos seguros contratados, menor a taxa de risco a ser considerada no BDI. Sendo assim, optou-se por representá-las na planilha de forma unificada. Poderão estar contabilizados na parcela os Seguros de Risco de Engenharia e de Responsabilidade Civil, dentre outros. 4 - Conforme orientações do TCU, publicadas no guia ORIENTAÇÕES PARA ELABORAÇÃO DE PLANILHAS ORÇAMENTÁRIAS DE OBRAS PÚBLICAS, a CPRB (Contribuição Previdenciária Sobre a Receita Bruta) deve ser incluída no cálculo do BDI de orçamentos que consideram a desoneração da folha de pagamentos.
B28: Observação: O PROPONENTE utilizará a incidência da CPRB somente se estiver enquadrado como desonerado.
